{
    "session_id": "9e69bf6df5935c59785d01ef3151c075",
    "player_info": {
        "player": {
            "player_id": 1819,
            "current_sector": 1,
            "unread_news_count": 0,
            "session_token": "9e69bf6df5935c59785d01ef3151c075",
            "id": 1819,
            "username": "ai_qa_bot_003",
            "credits": "3360.00",
            "turns_remaining": 99999,
            "sector": 1,
            "ship_id": 137,
            "corp_id": 0,
            "alignment": 1,
            "experience": 0
        }
    },
    "ship_info": {
        "id": 137,
        "name": "ai_qa_bot_003's ship",
        "type_id": 2,
        "holds": 10,
        "fighters": 1,
        "shields": 1,
        "onplanet": 0,
        "ported": 0,
        "cargo": [
            {
                "commodity": "ore",
                "quantity": 9
            }
        ]
    },
    "player_location_sector": 1,
    "sector_data": {
        "1": {
            "server_tick": 396,
            "sector_id": 1,
            "name": "Fedspace 1",
            "beacon": "The Federation -- Do Not Dump!",
            "adjacent_sectors": [
                {
                    "to_sector": 2
                },
                {
                    "to_sector": 3
                },
                {
                    "to_sector": 4
                },
                {
                    "to_sector": 5
                },
                {
                    "to_sector": 6
                },
                {
                    "to_sector": 7
                }
            ],
            "ships_present": [
                {
                    "ship_id": 1,
                    "name": "Used Scout Marauder"
                },
                {
                    "ship_id": 2,
                    "name": "Used Scout Marauder"
                },
                {
                    "ship_id": 3,
                    "name": "Bit Banger"
                },
                {
                    "ship_id": 4,
                    "name": "Used Scout Marauder"
                },
                {
                    "ship_id": 1018,
                    "name": "MoverShip"
                },
                {
                    "ship_id": 17,
                    "name": "Used Scout Marauder"
                },
                {
                    "ship_id": 1003,
                    "name": "USS Upgrade Me"
                },
                {
                    "ship_id": 1004,
                    "name": "USS Genesis"
                },
                {
                    "ship_id": 1006,
                    "name": "StatusShip"
                },
                {
                    "ship_id": 1011,
                    "name": "CaptainShip"
                },
                {
                    "ship_id": 1005,
                    "name": "TraderShip"
                },
                {
                    "ship_id": 1002,
                    "name": "VictimShip"
                },
                {
                    "ship_id": 1019,
                    "name": "ObserverShip"
                },
                {
                    "ship_id": 6,
                    "name": "Used Scout Marauder"
                },
                {
                    "ship_id": 12,
                    "name": "Used Scout Marauder"
                },
                {
                    "ship_id": 34,
                    "name": "Used Scout Marauder"
                },
                {
                    "ship_id": 41,
                    "name": "Used Scout Marauder"
                },
                {
                    "ship_id": 85,
                    "name": "Used Scout Marauder"
                },
                {
                    "ship_id": 90,
                    "name": "Used Scout Marauder"
                },
                {
                    "ship_id": 91,
                    "name": "Used Scout Marauder"
                },
                {
                    "ship_id": 97,
                    "name": "Used Scout Marauder"
                },
                {
                    "ship_id": 119,
                    "name": "Used Scout Marauder"
                },
                {
                    "ship_id": 103,
                    "name": "Used Scout Marauder"
                },
                {
                    "ship_id": 110,
                    "name": "Used Scout Marauder"
                },
                {
                    "ship_id": 154,
                    "name": "ai_qa_bot_020's ship"
                },
                {
                    "ship_id": 152,
                    "name": "ai_qa_bot_018's ship"
                },
                {
                    "ship_id": 142,
                    "name": "ai_qa_bot_008's ship"
                },
                {
                    "ship_id": 158,
                    "name": "ai_qa_bot_024's ship"
                },
                {
                    "ship_id": 156,
                    "name": "ai_qa_bot_022's ship"
                },
                {
                    "ship_id": 157,
                    "name": "ai_qa_bot_023's ship"
                },
                {
                    "ship_id": 140,
                    "name": "ai_qa_bot_006's ship"
                },
                {
                    "ship_id": 149,
                    "name": "ai_qa_bot_015's ship"
                },
                {
                    "ship_id": 150,
                    "name": "ai_qa_bot_016's ship"
                },
                {
                    "ship_id": 146,
                    "name": "ai_qa_bot_012's ship"
                },
                {
                    "ship_id": 145,
                    "name": "ai_qa_bot_011's ship"
                },
                {
                    "ship_id": 155,
                    "name": "ai_qa_bot_021's ship"
                },
                {
                    "ship_id": 141,
                    "name": "ai_qa_bot_007's ship"
                },
                {
                    "ship_id": 148,
                    "name": "ai_qa_bot_014's ship"
                },
                {
                    "ship_id": 147,
                    "name": "ai_qa_bot_013's ship"
                },
                {
                    "ship_id": 153,
                    "name": "ai_qa_bot_019's ship"
                },
                {
                    "ship_id": 139,
                    "name": "ai_qa_bot_005's ship"
                },
                {
                    "ship_id": 137,
                    "name": "ai_qa_bot_003's ship"
                }
            ],
            "ports": [
                {
                    "port_id": 1,
                    "name": "Tavern Central",
                    "type": 10
                },
                {
                    "port_id": 2,
                    "name": "Trader Outpost",
                    "type": 1
                },
                {
                    "port_id": 9,
                    "name": "Stardock Prime",
                    "type": 9
                }
            ],
            "celestial_objects": [
                {
                    "planet_id": 1,
                    "name": "Terra",
                    "type": 1
                },
                {
                    "planet_id": 900,
                    "name": "Target",
                    "type": 0
                },
                {
                    "planet_id": 200,
                    "name": "Dune",
                    "type": 0
                },
                {
                    "planet_id": 700,
                    "name": "MyWorld",
                    "type": 0
                }
            ],
            "counts": {
                "fighters": 0,
                "mines": 0
            },
            "_last_refreshed": 1768139898.5218732,
            "has_port": true,
            "has_planet": true,
            "adjacent": [
                {
                    "to_sector": 2
                },
                {
                    "to_sector": 3
                },
                {
                    "to_sector": 4
                },
                {
                    "to_sector": 5
                },
                {
                    "to_sector": 6
                },
                {
                    "to_sector": 7
                }
            ]
        }
    },
    "universe_map": {
        "1": {
            "is_explored": true,
            "has_port": true
        }
    },
    "port_info_by_sector": {},
    "price_cache": {},
    "bank_balance": 0,
    "command_retry_info": {
        "player.my_info": {
            "next_retry_time": 1768139900.3780546
        },
        "ship.info": {
            "next_retry_time": 1768139901.5050287
        },
        "sector.info": {
            "next_retry_time": 1768139902.5176358
        }
    },
    "strategy_plan": [],
    "trade_successful": false,
    "q_table": {},
    "n_table": {},
    "command_schemas": {
        "admin.notice": {
            "$id": "ge://schema/admin.notice.json",
            "$schema": "https://json-schema.org/draft/2020-12/schema",
            "type": "object"
        },
        "admin.shutdown_warning": {
            "$id": "ge://schema/admin.shutdown_warning.json",
            "$schema": "https://json-schema.org/draft/2020-12/schema",
            "type": "object"
        },
        "auth.login": {
            "$id": "ge://schema/auth.login.json",
            "$schema": "https://json-schema.org/draft/2020-12/schema",
            "type": "object",
            "properties": {
                "username": {
                    "type": "string"
                },
                "passwd": {
                    "type": "string"
                }
            },
            "required": [
                "username",
                "passwd"
            ],
            "additionalProperties": false
        },
        "auth.logout": {
            "$id": "ge://schema/auth.logout.json",
            "$schema": "https://json-schema.org/draft/2020-12/schema",
            "type": "object",
            "properties": {},
            "additionalProperties": false
        },
        "auth.mfa.totp.verify": {
            "$id": "ge://schema/auth.mfa.totp.verify.json",
            "$schema": "https://json-schema.org/draft/2020-12/schema",
            "type": "object",
            "properties": {
                "code": {
                    "type": "string",
                    "pattern": "^[0-9]{6}$"
                }
            },
            "required": [
                "code"
            ],
            "additionalProperties": false
        },
        "auth.register": {
            "$id": "ge://schema/auth.register.json",
            "$schema": "https://json-schema.org/draft/2020-12/schema",
            "type": "object",
            "required": [
                "username",
                "passwd"
            ],
            "additionalProperties": false,
            "properties": {
                "username": {
                    "type": "string"
                },
                "passwd": {
                    "type": "string"
                },
                "ship_name": {
                    "type": "string"
                },
                "ui_locale": {
                    "type": "string"
                },
                "ui_timezone": {
                    "type": "string"
                }
            }
        },
        "auth.refresh": {
            "$id": "ge://schema/auth.refresh.json",
            "$schema": "https://json-schema.org/draft/2020-12/schema",
            "type": "object",
            "properties": {},
            "additionalProperties": false
        },
        "bank.balance": {
            "$id": "ge://schema/bank.balance.json",
            "$schema": "https://json-schema.org/draft/2020-12/schema",
            "type": "object",
            "properties": {},
            "required": [],
            "additionalProperties": false
        },
        "bank.deposit": {
            "$id": "ge://schema/placeholder.json",
            "$comment": "Not yet implemented",
            "type": "object"
        },
        "bank.history": {
            "$id": "ge://schema/bank.history.json",
            "$schema": "https://json-schema.org/draft/2020-12/schema",
            "type": "object",
            "required": [],
            "additionalProperties": false,
            "properties": {
                "limit": {
                    "type": "integer",
                    "minimum": 1,
                    "maximum": 50
                },
                "cursor": {
                    "type": "string"
                },
                "tx_type": {
                    "type": "string",
                    "enum": [
                        "DEPOSIT",
                        "WITHDRAWAL",
                        "TRANSFER",
                        "INTEREST",
                        "FEE",
                        "WIRE",
                        "TAX",
                        "TRADE_BUY_FEE",
                        "TRADE_SELL_FEE",
                        "WITHDRAWAL_FEE",
                        "ADJUSTMENT"
                    ]
                },
                "start_date": {
                    "type": "integer"
                },
                "end_date": {
                    "type": "integer"
                },
                "min_amount": {
                    "type": "integer",
                    "minimum": 0
                },
                "max_amount": {
                    "type": "integer",
                    "minimum": 0
                }
            }
        },
        "bank.leaderboard": {
            "$id": "ge://schema/bank.leaderboard.json",
            "$schema": "https://json-schema.org/draft/2020-12/schema",
            "type": "object",
            "properties": {
                "limit": {
                    "type": "integer",
                    "minimum": 1,
                    "maximum": 100
                }
            },
            "required": [],
            "additionalProperties": false
        },
        "bank.transfer": {
            "$id": "ge://schema/placeholder.json",
            "$comment": "Not yet implemented",
            "type": "object"
        },
        "bank.withdraw": {
            "$id": "ge://schema/placeholder.json",
            "$comment": "Not yet implemented",
            "type": "object"
        },
        "bounty.list": {
            "$id": "ge://schema/placeholder.json",
            "$comment": "Not yet implemented",
            "type": "object"
        },
        "bounty.post_federation": {
            "$id": "ge://schema/placeholder.json",
            "$comment": "Not yet implemented",
            "type": "object"
        },
        "bounty.post_hitlist": {
            "$id": "ge://schema/placeholder.json",
            "$comment": "Not yet implemented",
            "type": "object"
        },
        "bulk.execute": {
            "$id": "ge://schema/bulk.execute.json",
            "$schema": "https://json-schema.org/draft/2020-12/schema",
            "type": "object",
            "properties": {
                "commands": {
                    "type": "array",
                    "minItems": 1
                }
            },
            "required": [
                "commands"
            ],
            "additionalProperties": false
        },
        "fine.list": {
            "$id": "ge://schema/fine.list.json",
            "$schema": "https://json-schema.org/draft/2020-12/schema",
            "type": "object",
            "properties": {},
            "required": [],
            "additionalProperties": false
        },
        "fine.pay": {
            "$id": "ge://schema/fine.pay.json",
            "$schema": "https://json-schema.org/draft/2020-12/schema",
            "type": "object",
            "properties": {
                "fine_id": {
                    "type": "integer"
                },
                "amount": {
                    "type": "integer"
                }
            },
            "required": [
                "fine_id"
            ],
            "additionalProperties": false
        },
        "insurance.policies.list": {
            "$id": "ge://schema/insurance.policies.list.json",
            "$schema": "https://json-schema.org/draft/2020-12/schema",
            "type": "object",
            "properties": {},
            "required": [],
            "additionalProperties": false
        },
        "insurance.policies.buy": {
            "$id": "ge://schema/insurance.policies.buy.json",
            "$schema": "https://json-schema.org/draft/2020-12/schema",
            "type": "object",
            "properties": {
                "subject_type": {
                    "type": "string",
                    "enum": [
                        "ship",
                        "cargo",
                        "planet"
                    ]
                },
                "subject_id": {
                    "type": "integer"
                },
                "duration": {
                    "type": "integer"
                },
                "premium": {
                    "type": "integer"
                }
            },
            "required": [
                "subject_type",
                "subject_id",
                "duration",
                "premium"
            ],
            "additionalProperties": false
        },
        "insurance.claim.file": {
            "$id": "ge://schema/insurance.claim.file.json",
            "$schema": "https://json-schema.org/draft/2020-12/schema",
            "type": "object",
            "properties": {
                "policy_id": {
                    "type": "integer"
                },
                "incident_description": {
                    "type": "string"
                }
            },
            "required": [
                "policy_id",
                "incident_description"
            ],
            "additionalProperties": false
        },
        "chat.broadcast": {
            "$id": "ge://schema/chat.broadcast.json",
            "$schema": "https://json-schema.org/draft/2020-12/schema",
            "type": "object",
            "properties": {
                "message": {
                    "type": "string",
                    "minLength": 1
                }
            },
            "required": [
                "message"
            ],
            "additionalProperties": false
        },
        "chat.history": {
            "$id": "ge://schema/chat.history.json",
            "$schema": "https://json-schema.org/draft/2020-12/schema",
            "type": "object",
            "properties": {
                "channel": {
                    "type": "string"
                },
                "limit": {
                    "type": "integer",
                    "minimum": 1,
                    "maximum": 100
                }
            },
            "additionalProperties": false
        },
        "chat.send": {
            "$id": "ge://schema/chat.send.json",
            "$schema": "https://json-schema.org/draft/2020-12/schema",
            "type": "object",
            "properties": {
                "channel": {
                    "type": "string"
                },
                "message": {
                    "type": "string",
                    "minLength": 1
                }
            },
            "required": [
                "channel",
                "message"
            ],
            "additionalProperties": false
        },
        "citadel.build": {
            "$id": "ge://schema/citadel.build.json",
            "$schema": "https://json-schema.org/draft/2020-12/schema",
            "type": "object",
            "properties": {
                "sector_id": {
                    "type": "integer",
                    "minimum": 1
                }
            },
            "required": [
                "sector_id"
            ],
            "additionalProperties": false
        },
        "citadel.upgrade": {
            "$id": "ge://schema/citadel.upgrade.json",
            "$schema": "https://json-schema.org/draft/2020-12/schema",
            "type": "object",
            "properties": {
                "citadel_id": {
                    "type": "integer",
                    "minimum": 1
                }
            },
            "required": [
                "citadel_id"
            ],
            "additionalProperties": false
        },
        "combat.attack": {
            "$id": "ge://schema/combat.attack.json",
            "$schema": "https://json-schema.org/draft/2020-12/schema",
            "type": "object",
            "properties": {
                "target_ship_id": {
                    "type": "integer",
                    "minimum": 1
                }
            },
            "required": [
                "target_ship_id"
            ],
            "additionalProperties": false
        },
        "combat.attack_planet": {
            "$id": "ge://schema/placeholder.json",
            "$comment": "Not yet implemented",
            "type": "object"
        },
        "combat.deploy_fighters": {
            "$id": "ge://schema/combat.deploy_fighters.json",
            "$schema": "https://json-schema.org/draft/2020-12/schema",
            "type": "object",
            "required": [
                "amount",
                "offense"
            ],
            "additionalProperties": false,
            "properties": {
                "amount": {
                    "type": "integer"
                },
                "offense": {
                    "type": "integer"
                },
                "corporation_id": {
                    "type": "integer"
                }
            }
        },
        "combat.deploy_mines": {
            "$id": "ge://schema/combat.deploy_mines.json",
            "$schema": "https://json-schema.org/draft/2020-12/schema",
            "type": "object",
            "required": [
                "amount",
                "offense"
            ],
            "additionalProperties": false,
            "properties": {
                "amount": {
                    "type": "integer"
                },
                "offense": {
                    "type": "integer"
                },
                "corporation_id": {
                    "type": "integer"
                },
                "mine_type": {
                    "type": "integer"
                }
            }
        },
        "combat.lay_mines": {
            "$id": "ge://schema/combat.lay_mines.json",
            "$schema": "https://json-schema.org/draft/2020-12/schema",
            "type": "object",
            "properties": {
                "quantity": {
                    "type": "integer",
                    "minimum": 1
                }
            },
            "required": [
                "quantity"
            ],
            "additionalProperties": false
        },
        "combat.status": {
            "$id": "ge://schema/combat.status.json",
            "$schema": "https://json-schema.org/draft/2020-12/schema",
            "type": "object",
            "properties": {},
            "additionalProperties": false
        },
        "combat.sweep_mines": {
            "$id": "ge://schema/combat.sweep_mines.json",
            "$schema": "https://json-schema.org/draft/2020-12/schema",
            "type": "object",
            "properties": {},
            "additionalProperties": false
        },
        "deploy.fighters.list": {
            "$id": "ge://schema/deploy.fighters.list.json",
            "$schema": "https://json-schema.org/draft/2020-12/schema",
            "type": "object",
            "properties": {},
            "required": [],
            "additionalProperties": false
        },
        "deploy.mines.list": {
            "$id": "ge://schema/deploy.mines.list.json",
            "$schema": "https://json-schema.org/draft/2020-12/schema",
            "type": "object",
            "properties": {},
            "required": [],
            "additionalProperties": false
        },
        "fighters.recall": {
            "$id": "ge://schema/fighters.recall.json",
            "$schema": "https://json-schema.org/draft/2020-12/schema",
            "type": "object",
            "required": [
                "sector_id",
                "asset_id"
            ],
            "additionalProperties": false,
            "properties": {
                "sector_id": {
                    "type": "integer"
                },
                "asset_id": {
                    "type": "integer"
                }
            }
        },
        "mines.recall": {
            "$id": "ge://schema/mines.recall.json",
            "$schema": "https://json-schema.org/draft/2020-12/schema",
            "type": "object",
            "required": [
                "sector_id",
                "asset_id"
            ],
            "additionalProperties": false,
            "properties": {
                "sector_id": {
                    "type": "integer"
                },
                "asset_id": {
                    "type": "integer"
                }
            }
        },
        "corp.balance": {
            "$id": "ge://schema/placeholder.json",
            "$comment": "Not yet implemented",
            "type": "object"
        },
        "corp.create": {
            "$id": "ge://schema/placeholder.json",
            "$comment": "Not yet implemented",
            "type": "object"
        },
        "corp.deposit": {
            "$id": "ge://schema/placeholder.json",
            "$comment": "Not yet implemented",
            "type": "object"
        },
        "corp.dissolve": {
            "$id": "ge://schema/placeholder.json",
            "$comment": "Not yet implemented",
            "type": "object"
        },
        "corp.invite": {
            "$id": "ge://schema/placeholder.json",
            "$comment": "Not yet implemented",
            "type": "object"
        },
        "corp.join": {
            "$id": "ge://schema/placeholder.json",
            "$comment": "Not yet implemented",
            "type": "object"
        },
        "corp.kick": {
            "$id": "ge://schema/placeholder.json",
            "$comment": "Not yet implemented",
            "type": "object"
        },
        "corp.leave": {
            "$id": "ge://schema/placeholder.json",
            "$comment": "Not yet implemented",
            "type": "object"
        },
        "corp.list": {
            "$id": "ge://schema/placeholder.json",
            "$comment": "Not yet implemented",
            "type": "object"
        },
        "corp.roster": {
            "$id": "ge://schema/placeholder.json",
            "$comment": "Not yet implemented",
            "type": "object"
        },
        "corp.statement": {
            "$id": "ge://schema/placeholder.json",
            "$comment": "Not yet implemented",
            "type": "object"
        },
        "corp.status": {
            "$id": "ge://schema/placeholder.json",
            "$comment": "Not yet implemented",
            "type": "object"
        },
        "corp.transfer_ceo": {
            "$id": "ge://schema/placeholder.json",
            "$comment": "Not yet implemented",
            "type": "object"
        },
        "corp.withdraw": {
            "$id": "ge://schema/placeholder.json",
            "$comment": "Not yet implemented",
            "type": "object"
        },
        "dock.status": {
            "$id": "ge://schema/placeholder.json",
            "$comment": "Not yet implemented",
            "type": "object"
        },
        "hardware.buy": {
            "$id": "ge://schema/hardware.buy.json",
            "$schema": "https://json-schema.org/draft/2020-12/schema",
            "type": "object",
            "properties": {
                "code": {
                    "type": "string"
                },
                "quantity": {
                    "type": "integer",
                    "minimum": 1
                },
                "idempotency_key": {
                    "type": "string"
                }
            },
            "required": [
                "code",
                "quantity"
            ],
            "additionalProperties": false
        },
        "hardware.list": {
            "$id": "ge://schema/hardware.list.json",
            "$schema": "https://json-schema.org/draft/2020-12/schema",
            "type": "object",
            "properties": {},
            "required": [],
            "additionalProperties": false
        },
        "mail.delete": {
            "$id": "ge://schema/mail.delete.json",
            "$schema": "https://json-schema.org/draft/2020-12/schema",
            "type": "object",
            "properties": {
                "mail_id": {
                    "type": "integer",
                    "minimum": 1
                }
            },
            "required": [
                "mail_id"
            ],
            "additionalProperties": false
        },
        "mail.inbox": {
            "$id": "ge://schema/mail.inbox.json",
            "$schema": "https://json-schema.org/draft/2020-12/schema",
            "type": "object",
            "properties": {},
            "required": [],
            "additionalProperties": false
        },
        "mail.read": {
            "$id": "ge://schema/mail.read.json",
            "$schema": "https://json-schema.org/draft/2020-12/schema",
            "type": "object",
            "required": [
                "mail_id"
            ],
            "additionalProperties": false,
            "properties": {
                "mail_id": {
                    "type": "integer"
                }
            }
        },
        "mail.send": {
            "$id": "ge://schema/mail.send.json",
            "$schema": "https://json-schema.org/draft/2020-12/schema",
            "type": "object",
            "properties": {
                "to_player_name": {
                    "type": "string"
                },
                "subject": {
                    "type": "string"
                },
                "body": {
                    "type": "string"
                }
            },
            "required": [
                "to_player_name",
                "subject",
                "body"
            ],
            "additionalProperties": false
        },
        "move.autopilot.start": {
            "$id": "ge://schema/move.autopilot.start.json",
            "$schema": "https://json-schema.org/draft/2020-12/schema",
            "type": "object",
            "properties": {
                "to_sector_id": {
                    "type": "integer",
                    "minimum": 1
                }
            },
            "required": [
                "to_sector_id"
            ],
            "additionalProperties": false
        },
        "move.autopilot.status": {
            "$id": "ge://schema/move.autopilot.status.json",
            "$schema": "https://json-schema.org/draft/2020-12/schema",
            "type": "object",
            "properties": {},
            "required": [],
            "additionalProperties": false
        },
        "move.autopilot.stop": {
            "$id": "ge://schema/move.autopilot.stop.json",
            "$schema": "https://json-schema.org/draft/2020-12/schema",
            "type": "object",
            "properties": {},
            "additionalProperties": false
        },
        "move.describe_sector": {
            "$id": "ge://schema/move.describe_sector.json",
            "$schema": "https://json-schema.org/draft/2020-12/schema",
            "type": "object",
            "properties": {
                "sector_id": {
                    "type": "integer",
                    "minimum": 1
                }
            },
            "required": [
                "sector_id"
            ],
            "additionalProperties": false
        },
        "move.pathfind": {
            "$id": "ge://schema/move.pathfind.json",
            "$schema": "https://json-schema.org/draft/2020-12/schema",
            "type": "object",
            "properties": {
                "from_sector_id": {
                    "type": "integer",
                    "minimum": 1
                },
                "to_sector_id": {
                    "type": "integer",
                    "minimum": 1
                }
            },
            "required": [
                "from_sector_id",
                "to_sector_id"
            ],
            "additionalProperties": false
        },
        "move.scan": {
            "$id": "ge://schema/move.scan.json",
            "$schema": "https://json-schema.org/draft/2020-12/schema",
            "type": "object",
            "properties": {}
        },
        "move.transwarp": {
            "$id": "ge://schema/placeholder.json",
            "$comment": "Not yet implemented",
            "type": "object"
        },
        "move.warp": {
            "$id": "ge://schema/move_warp.json",
            "$schema": "https://json-schema.org/draft/2020-12/schema",
            "type": "object",
            "properties": {
                "to_sector_id": {
                    "type": "integer"
                }
            },
            "required": [
                "to_sector_id"
            ],
            "additionalProperties": false
        },
        "nav.avoid.add": {
            "$id": "ge://schema/placeholder.json",
            "$comment": "Not yet implemented",
            "type": "object"
        },
        "nav.avoid.list": {
            "$id": "ge://schema/placeholder.json",
            "$comment": "Not yet implemented",
            "type": "object"
        },
        "nav.avoid.remove": {
            "$id": "ge://schema/placeholder.json",
            "$comment": "Not yet implemented",
            "type": "object"
        },
        "nav.avoid.set": {
            "$id": "ge://schema/placeholder.json",
            "$comment": "Not yet implemented",
            "type": "object"
        },
        "nav.bookmark.add": {
            "$id": "ge://schema/placeholder.json",
            "$comment": "Not yet implemented",
            "type": "object"
        },
        "nav.bookmark.list": {
            "$id": "ge://schema/placeholder.json",
            "$comment": "Not yet implemented",
            "type": "object"
        },
        "nav.bookmark.remove": {
            "$id": "ge://schema/placeholder.json",
            "$comment": "Not yet implemented",
            "type": "object"
        },
        "nav.bookmark.set": {
            "$id": "ge://schema/placeholder.json",
            "$comment": "Not yet implemented",
            "type": "object"
        },
        "news.get_feed": {
            "$id": "ge://schema/placeholder.json",
            "$comment": "Not yet implemented",
            "type": "object"
        },
        "news.mark_feed_read": {
            "$id": "ge://schema/placeholder.json",
            "$comment": "Not yet implemented",
            "type": "object"
        },
        "news.read": {
            "$id": "ge://schema/news.read.json",
            "$schema": "https://json-schema.org/draft/2020-12/schema",
            "type": "object",
            "properties": {},
            "required": [],
            "additionalProperties": false
        },
        "notes.list": {
            "$id": "ge://schema/placeholder.json",
            "$comment": "Not yet implemented",
            "type": "object"
        },
        "notice.ack": {
            "$id": "ge://schema/notice.ack.json",
            "$schema": "https://json-schema.org/draft/2020-12/schema",
            "type": "object",
            "properties": {
                "notice_id": {
                    "type": "integer"
                }
            },
            "required": [
                "notice_id"
            ],
            "additionalProperties": false
        },
        "notice.list": {
            "$id": "ge://schema/notice.list.json",
            "$schema": "https://json-schema.org/draft/2020-12/schema",
            "type": "object",
            "properties": {},
            "required": [],
            "additionalProperties": false
        },
        "planet.create": {
            "$id": "ge://schema/planet.genesis_create.json",
            "$schema": "https://json-schema.org/draft/2020-12/schema",
            "type": "object",
            "properties": {
                "sector_id": {
                    "type": "integer"
                },
                "name": {
                    "type": "string"
                },
                "owner_entity_type": {
                    "type": "string",
                    "enum": [
                        "player",
                        "corporation"
                    ]
                },
                "idempotency_key": {
                    "type": "string"
                }
            },
            "required": [
                "sector_id",
                "name",
                "owner_entity_type"
            ],
            "additionalProperties": false
        },
        "planet.deposit": {
            "$id": "ge://schema/planet.deposit.json",
            "$schema": "https://json-schema.org/draft/2020-12/schema",
            "type": "object",
            "properties": {
                "planet_id": {
                    "type": "integer",
                    "minimum": 1
                },
                "commodity": {
                    "type": "string"
                },
                "quantity": {
                    "type": "integer",
                    "minimum": 1
                }
            },
            "required": [
                "planet_id",
                "commodity",
                "quantity"
            ],
            "additionalProperties": false
        },
        "planet.genesis": {
            "$id": "ge://schema/planet.genesis.json",
            "$schema": "https://json-schema.org/draft/2020-12/schema",
            "type": "object",
            "properties": {
                "name": {
                    "type": "string",
                    "minLength": 1
                }
            },
            "required": [
                "name"
            ],
            "additionalProperties": false
        },
        "planet.genesis_create": {
            "$id": "ge://schema/planet.genesis_create.json",
            "$schema": "https://json-schema.org/draft/2020-12/schema",
            "type": "object",
            "properties": {
                "sector_id": {
                    "type": "integer"
                },
                "name": {
                    "type": "string"
                },
                "owner_entity_type": {
                    "type": "string",
                    "enum": [
                        "player",
                        "corporation"
                    ]
                },
                "idempotency_key": {
                    "type": "string"
                }
            },
            "required": [
                "sector_id",
                "name",
                "owner_entity_type"
            ],
            "additionalProperties": false
        },
        "planet.harvest": {
            "$id": "ge://schema/planet.harvest.json",
            "$schema": "https://json-schema.org/draft/2020-12/schema",
            "type": "object",
            "properties": {
                "planet_id": {
                    "type": "integer",
                    "minimum": 1
                }
            },
            "required": [
                "planet_id"
            ],
            "additionalProperties": false
        },
        "planet.info": {
            "$id": "ge://schema/planet.info.json",
            "$schema": "https://json-schema.org/draft/2020-12/schema",
            "type": "object",
            "properties": {
                "planet_id": {
                    "type": "integer",
                    "minimum": 1
                }
            },
            "required": [
                "planet_id"
            ],
            "additionalProperties": false
        },
        "planet.land": {
            "$id": "ge://schema/planet.land.json",
            "$schema": "https://json-schema.org/draft/2020-12/schema",
            "type": "object",
            "properties": {
                "planet_id": {
                    "type": "integer",
                    "minimum": 1
                }
            },
            "required": [
                "planet_id"
            ],
            "additionalProperties": false
        },
        "planet.launch": {
            "$id": "ge://schema/planet.launch.json",
            "$schema": "https://json-schema.org/draft/2020-12/schema",
            "type": "object",
            "properties": {},
            "additionalProperties": false
        },
        "planet.market.buy_order": {
            "$id": "ge://schema/placeholder.json",
            "$comment": "Not yet implemented",
            "type": "object"
        },
        "planet.market.sell": {
            "$id": "ge://schema/placeholder.json",
            "$comment": "Not yet implemented",
            "type": "object"
        },
        "planet.rename": {
            "$id": "ge://schema/planet.rename.json",
            "$schema": "https://json-schema.org/draft/2020-12/schema",
            "type": "object",
            "properties": {
                "planet_id": {
                    "type": "integer",
                    "minimum": 1
                },
                "name": {
                    "type": "string",
                    "minLength": 1
                }
            },
            "required": [
                "planet_id",
                "name"
            ],
            "additionalProperties": false
        },
        "planet.transfer_ownership": {
            "$id": "ge://schema/planet.transfer_ownership.json",
            "$schema": "https://json-schema.org/draft/2020-12/schema",
            "type": "object",
            "properties": {
                "planet_id": {
                    "type": "integer",
                    "minimum": 1
                },
                "new_owner_id": {
                    "type": "integer",
                    "minimum": 1
                }
            },
            "required": [
                "planet_id",
                "new_owner_id"
            ],
            "additionalProperties": false
        },
        "planet.withdraw": {
            "$id": "ge://schema/planet.withdraw.json",
            "$schema": "https://json-schema.org/draft/2020-12/schema",
            "type": "object",
            "properties": {
                "planet_id": {
                    "type": "integer",
                    "minimum": 1
                },
                "commodity": {
                    "type": "string"
                },
                "quantity": {
                    "type": "integer",
                    "minimum": 1
                }
            },
            "required": [
                "planet_id",
                "commodity",
                "quantity"
            ],
            "additionalProperties": false
        },
        "player.get_avoids": {
            "$id": "ge://schema/placeholder.json",
            "$comment": "Not yet implemented",
            "type": "object"
        },
        "player.get_bookmarks": {
            "$id": "ge://schema/placeholder.json",
            "$comment": "Not yet implemented",
            "type": "object"
        },
        "player.get_notes": {
            "$id": "ge://schema/placeholder.json",
            "$comment": "Not yet implemented",
            "type": "object"
        },
        "player.get_prefs": {
            "$id": "ge://schema/placeholder.json",
            "$comment": "Not yet implemented",
            "type": "object"
        },
        "player.get_settings": {
            "$id": "ge://schema/placeholder.json",
            "$comment": "Not yet implemented",
            "type": "object"
        },
        "player.get_subscriptions": {
            "$id": "ge://schema/placeholder.json",
            "$comment": "Not yet implemented",
            "type": "object"
        },
        "player.get_topics": {
            "$id": "ge://schema/placeholder.json",
            "$comment": "Not yet implemented",
            "type": "object"
        },
        "player.my_info": {
            "$id": "ge://schema/player.my_info.json",
            "$schema": "https://json-schema.org/draft/2020-12/schema",
            "type": "object",
            "properties": {},
            "required": [],
            "additionalProperties": false
        },
        "player.rankings": {
            "$id": "ge://schema/placeholder.json",
            "$comment": "Not yet implemented",
            "type": "object"
        },
        "player.set_avoids": {
            "$id": "ge://schema/placeholder.json",
            "$comment": "Not yet implemented",
            "type": "object"
        },
        "player.set_bookmarks": {
            "$id": "ge://schema/placeholder.json",
            "$comment": "Not yet implemented",
            "type": "object"
        },
        "player.set_prefs": {
            "$id": "ge://schema/placeholder.json",
            "$comment": "Not yet implemented",
            "type": "object"
        },
        "player.set_settings": {
            "$id": "ge://schema/placeholder.json",
            "$comment": "Not yet implemented",
            "type": "object"
        },
        "player.set_subscriptions": {
            "$id": "ge://schema/placeholder.json",
            "$comment": "Not yet implemented",
            "type": "object"
        },
        "player.set_topics": {
            "$id": "ge://schema/placeholder.json",
            "$comment": "Not yet implemented",
            "type": "object"
        },
        "player.set_trade_account_preference": {
            "$id": "ge://schema/player.set_trade_account_preference.json",
            "$schema": "https://json-schema.org/draft/2020-12/schema",
            "type": "object",
            "properties": {
                "preference": {
                    "type": "integer",
                    "enum": [
                        0,
                        1
                    ]
                }
            },
            "required": [
                "preference"
            ],
            "additionalProperties": false
        },
        "port.describe": {
            "$id": "ge://schema/port.describe.json",
            "$schema": "https://json-schema.org/draft/2020-12/schema",
            "type": "object",
            "properties": {
                "port_id": {
                    "type": "integer"
                },
                "sector_id": {
                    "type": "integer"
                }
            },
            "anyOf": [
                {
                    "required": [
                        "port_id"
                    ]
                },
                {
                    "required": [
                        "sector_id"
                    ]
                }
            ],
            "additionalProperties": false
        },
        "port.info": {
            "$id": "ge://schema/port.info.json",
            "$schema": "https://json-schema.org/draft/2020-12/schema",
            "type": "object",
            "properties": {},
            "additionalProperties": false
        },
        "port.rob": {
            "$id": "ge://schema/port.rob.json",
            "$schema": "https://json-schema.org/draft/2020-12/schema",
            "type": "object",
            "properties": {
                "sector_id": {
                    "type": "integer"
                },
                "port_id": {
                    "type": "integer"
                },
                "mode": {
                    "type": "string",
                    "enum": [
                        "credits",
                        "goods"
                    ]
                },
                "commodity": {
                    "type": "string"
                },
                "amount": {
                    "type": "integer",
                    "minimum": 1
                },
                "idempotency_key": {
                    "type": "string"
                }
            },
            "required": [
                "sector_id",
                "port_id",
                "mode",
                "idempotency_key"
            ],
            "additionalProperties": false
        },
        "port.status": {
            "$id": "ge://schema/port.status.json",
            "$schema": "https://json-schema.org/draft/2020-12/schema",
            "type": "object",
            "properties": {
                "port_id": {
                    "type": "integer"
                },
                "sector_id": {
                    "type": "integer"
                }
            },
            "anyOf": [
                {
                    "required": [
                        "port_id"
                    ]
                },
                {
                    "required": [
                        "sector_id"
                    ]
                }
            ],
            "additionalProperties": false
        },
        "sector.info": {
            "$id": "ge://schema/sector.info.json",
            "$schema": "https://json-schema.org/draft/2020-12/schema",
            "type": "object",
            "properties": {
                "sector_id": {
                    "type": "integer"
                }
            },
            "required": [],
            "additionalProperties": false
        },
        "sector.scan": {
            "$id": "ge://schema/sector.scan.json",
            "$schema": "https://json-schema.org/draft/2020-12/schema",
            "type": "object",
            "properties": {},
            "additionalProperties": false
        },
        "sector.scan.density": {
            "$id": "ge://schema/sector.scan.density.json",
            "$schema": "https://json-schema.org/draft/2020-12/schema",
            "type": "object",
            "properties": {},
            "additionalProperties": false
        },
        "sector.search": {
            "$id": "ge://schema/sector.search.json",
            "$schema": "https://json-schema.org/draft/2020-12/schema",
            "type": "object",
            "properties": {
                "query": {
                    "type": "string"
                }
            },
            "required": [
                "query"
            ],
            "additionalProperties": false
        },
        "sector.set_beacon": {
            "$id": "ge://schema/sector.set_beacon.json",
            "$schema": "https://json-schema.org/draft/2020-12/schema",
            "type": "object",
            "properties": {
                "sector_id": {
                    "type": "integer"
                },
                "text": {
                    "type": "string"
                }
            },
            "required": [
                "sector_id",
                "text"
            ],
            "additionalProperties": false
        },
        "session.disconnect": {
            "$id": "ge://schema/session.disconnect.json",
            "$schema": "https://json-schema.org/draft/2020-12/schema",
            "type": "object",
            "properties": {},
            "additionalProperties": false
        },
        "session.hello": {
            "$id": "ge://schema/session.hello.json",
            "$schema": "https://json-schema.org/draft/2020-12/schema",
            "type": "object",
            "properties": {},
            "required": [],
            "additionalProperties": false
        },
        "session.ping": {
            "$id": "ge://schema/session.ping.json",
            "$schema": "https://json-schema.org/draft/2020-12/schema",
            "type": "object",
            "properties": {},
            "required": [],
            "additionalProperties": false
        },
        "player.ping": {
            "$id": "ge://schema/session.ping.json",
            "$schema": "https://json-schema.org/draft/2020-12/schema",
            "type": "object",
            "properties": {},
            "required": [],
            "additionalProperties": false
        },
        "sys.notice.create": {
            "$id": "ge://schema/sys.notice.create.json",
            "$schema": "https://json-schema.org/draft/2020-12/schema",
            "type": "object",
            "properties": {
                "title": {
                    "type": "string"
                },
                "body": {
                    "type": "string"
                },
                "severity": {
                    "type": "string"
                },
                "expires_at": {
                    "type": "integer"
                }
            },
            "required": [
                "title",
                "body"
            ],
            "additionalProperties": false
        },
        "system.disconnect": {
            "$id": "ge://schema/system.disconnect.json",
            "$schema": "https://json-schema.org/draft/2020-12/schema",
            "type": "object",
            "properties": {},
            "additionalProperties": false
        },
        "ship.claim": {
            "$id": "ge://schema/ship.claim.json",
            "$schema": "https://json-schema.org/draft/2020-12/schema",
            "type": "object",
            "properties": {
                "ship_id": {
                    "type": "integer",
                    "minimum": 1
                }
            },
            "required": [
                "ship_id"
            ],
            "additionalProperties": false
        },
        "ship.info": {
            "$id": "ge://schema/ship.info.json",
            "$schema": "https://json-schema.org/draft/2020-12/schema",
            "type": "object",
            "properties": {
                "ship": {
                    "type": "object",
                    "properties": {
                        "id": {
                            "type": "integer"
                        },
                        "number": {
                            "type": "integer"
                        },
                        "name": {
                            "type": "string"
                        }
                    }
                }
            },
            "required": [
                "ship"
            ]
        },
        "ship.inspect": {
            "$id": "ge://schema/ship.inspect.json",
            "$schema": "https://json-schema.org/draft/2020-12/schema",
            "type": "object",
            "properties": {
                "ship_id": {
                    "type": "integer",
                    "minimum": 1
                }
            },
            "required": [
                "ship_id"
            ],
            "additionalProperties": false
        },
        "ship.jettison": {
            "$id": "ge://schema/ship.jettison.json",
            "$schema": "https://json-schema.org/draft/2020-12/schema",
            "type": "object",
            "properties": {
                "commodity_id": {
                    "type": "integer",
                    "minimum": 1
                },
                "quantity": {
                    "type": "integer",
                    "minimum": 1
                }
            },
            "required": [
                "commodity_id",
                "quantity"
            ],
            "additionalProperties": false
        },
        "ship.list": {
            "$id": "ge://schema/placeholder.json",
            "$comment": "Not yet implemented",
            "type": "object"
        },
        "ship.rename": {
            "$id": "ge://schema/ship.rename.json",
            "$schema": "https://json-schema.org/draft/2020-12/schema",
            "type": "object",
            "properties": {
                "name": {
                    "type": "string",
                    "minLength": 1,
                    "maxLength": 100
                }
            },
            "required": [
                "name"
            ],
            "additionalProperties": false
        },
        "ship.repair": {
            "$id": "ge://schema/ship.repair.json",
            "$schema": "https://json-schema.org/draft/2020-12/schema",
            "type": "object",
            "properties": {},
            "additionalProperties": false
        },
        "ship.reregister": {
            "$id": "ge://schema/ship.reregister.json",
            "$schema": "https://json-schema.org/draft/2020-12/schema",
            "type": "object",
            "properties": {
                "name": {
                    "type": "string",
                    "minLength": 1,
                    "maxLength": 100
                }
            },
            "required": [
                "name"
            ],
            "additionalProperties": false
        },
        "ship.self_destruct": {
            "$id": "ge://schema/ship.self_destruct.json",
            "$schema": "https://json-schema.org/draft/2020-12/schema",
            "type": "object",
            "properties": {},
            "additionalProperties": false
        },
        "ship.sell": {
            "$id": "ge://schema/placeholder.json",
            "$comment": "Not yet implemented",
            "type": "object"
        },
        "ship.status": {
            "$id": "ge://schema/ship.status.json",
            "$schema": "https://json-schema.org/draft/2020-12/schema",
            "type": "object",
            "properties": {
                "ship": {
                    "type": "object",
                    "properties": {
                        "id": {
                            "type": "integer"
                        },
                        "number": {
                            "type": "integer"
                        },
                        "name": {
                            "type": "string"
                        }
                    }
                }
            },
            "required": [
                "ship"
            ]
        },
        "ship.transfer": {
            "$id": "ge://schema/placeholder.json",
            "$comment": "Not yet implemented",
            "type": "object"
        },
        "ship.transfer_cargo": {
            "$id": "ge://schema/ship.transfer_cargo.json",
            "$schema": "https://json-schema.org/draft/2020-12/schema",
            "type": "object",
            "properties": {
                "commodity_id": {
                    "type": "integer",
                    "minimum": 1
                },
                "quantity": {
                    "type": "integer",
                    "minimum": 1
                },
                "target_ship_id": {
                    "type": "integer",
                    "minimum": 1
                }
            },
            "required": [
                "commodity_id",
                "quantity",
                "target_ship_id"
            ],
            "additionalProperties": false
        },
        "ship.upgrade": {
            "$id": "ge://schema/ship.upgrade.json",
            "$schema": "https://json-schema.org/draft/2020-12/schema",
            "type": "object",
            "properties": {
                "upgrade_type": {
                    "type": "string"
                }
            },
            "required": [
                "upgrade_type"
            ],
            "additionalProperties": false
        },
        "shipyard.list": {
            "$id": "ge://schema/placeholder.json",
            "$comment": "Not yet implemented",
            "type": "object"
        },
        "shipyard.sell": {
            "$id": "ge://schema/placeholder.json",
            "$comment": "Not yet implemented",
            "type": "object"
        },
        "shipyard.upgrade": {
            "$id": "ge://schema/placeholder.json",
            "$comment": "Not yet implemented",
            "type": "object"
        },
        "stock.buy": {
            "$id": "ge://schema/placeholder.json",
            "$comment": "Not yet implemented",
            "type": "object"
        },
        "stock.dividend.set": {
            "$id": "ge://schema/placeholder.json",
            "$comment": "Not yet implemented",
            "type": "object"
        },
        "stock.exchange.list_stocks": {
            "$id": "ge://schema/placeholder.json",
            "$comment": "Not yet implemented",
            "type": "object"
        },
        "stock.exchange.orders.cancel": {
            "$id": "ge://schema/placeholder.json",
            "$comment": "Not yet implemented",
            "type": "object"
        },
        "stock.exchange.orders.create": {
            "$id": "ge://schema/placeholder.json",
            "$comment": "Not yet implemented",
            "type": "object"
        },
        "stock.ipo.register": {
            "$id": "ge://schema/placeholder.json",
            "$comment": "Not yet implemented",
            "type": "object"
        },
        "stock.portfolio.list": {
            "$id": "ge://schema/placeholder.json",
            "$comment": "Not yet implemented",
            "type": "object"
        },
        "subscribe.add": {
            "$id": "ge://schema/subscribe.add.json",
            "$schema": "https://json-schema.org/draft/2020-12/schema",
            "type": "object",
            "properties": {
                "event_type": {
                    "type": "string"
                }
            },
            "required": [
                "event_type"
            ],
            "additionalProperties": false
        },
        "subscribe.catalog": {
            "$id": "ge://schema/subscribe.catalog.json",
            "$schema": "https://json-schema.org/draft/2020-12/schema",
            "type": "object",
            "properties": {},
            "required": [],
            "additionalProperties": false
        },
        "subscribe.list": {
            "$id": "ge://schema/subscribe.list.json",
            "$schema": "https://json-schema.org/draft/2020-12/schema",
            "type": "object",
            "properties": {},
            "additionalProperties": false
        },
        "subscribe.remove": {
            "$id": "ge://schema/subscribe.remove.json",
            "$schema": "https://json-schema.org/draft/2020-12/schema",
            "type": "object",
            "properties": {
                "event_type": {
                    "type": "string"
                }
            },
            "required": [
                "event_type"
            ],
            "additionalProperties": false
        },
        "tavern.barcharts.get_prices_summary": {
            "$id": "ge://schema/placeholder.json",
            "$comment": "Not yet implemented",
            "type": "object"
        },
        "tavern.deadpool.place_bet": {
            "$id": "ge://schema/placeholder.json",
            "$comment": "Not yet implemented",
            "type": "object"
        },
        "tavern.dice.play": {
            "$id": "ge://schema/placeholder.json",
            "$comment": "Not yet implemented",
            "type": "object"
        },
        "tavern.graffiti.post": {
            "$id": "ge://schema/placeholder.json",
            "$comment": "Not yet implemented",
            "type": "object"
        },
        "tavern.highstakes.play": {
            "$id": "ge://schema/placeholder.json",
            "$comment": "Not yet implemented",
            "type": "object"
        },
        "tavern.loan.pay": {
            "$id": "ge://schema/placeholder.json",
            "$comment": "Not yet implemented",
            "type": "object"
        },
        "tavern.loan.take": {
            "$id": "ge://schema/placeholder.json",
            "$comment": "Not yet implemented",
            "type": "object"
        },
        "tavern.lottery.buy_ticket": {
            "$id": "ge://schema/placeholder.json",
            "$comment": "Not yet implemented",
            "type": "object"
        },
        "tavern.lottery.status": {
            "$id": "ge://schema/placeholder.json",
            "$comment": "Not yet implemented",
            "type": "object"
        },
        "tavern.raffle.buy_ticket": {
            "$id": "ge://schema/placeholder.json",
            "$comment": "Not yet implemented",
            "type": "object"
        },
        "tavern.round.buy": {
            "$id": "ge://schema/placeholder.json",
            "$comment": "Not yet implemented",
            "type": "object"
        },
        "tavern.rumour.get_hint": {
            "$id": "ge://schema/placeholder.json",
            "$comment": "Not yet implemented",
            "type": "object"
        },
        "tavern.trader.buy_password": {
            "$id": "ge://schema/placeholder.json",
            "$comment": "Not yet implemented",
            "type": "object"
        },
        "trade.accept": {
            "$id": "ge://schema/trade.accept.json",
            "$schema": "https://json-schema.org/draft/2020-12/schema",
            "type": "object",
            "properties": {
                "trade_id": {
                    "type": "integer",
                    "minimum": 1
                }
            },
            "required": [
                "trade_id"
            ],
            "additionalProperties": false
        },
        "trade.buy": {
            "$id": "ge://schema/trade.buy.json",
            "$schema": "https://json-schema.org/draft/2020-12/schema",
            "type": "object",
            "required": [
                "port_id",
                "items",
                "idempotency_key",
                "account",
                "sector_id"
            ],
            "additionalProperties": false,
            "properties": {
                "port_id": {
                    "type": "integer"
                },
                "idempotency_key": {
                    "type": "string"
                },
                "account": {
                    "type": "integer",
                    "enum": [
                        0,
                        1
                    ]
                },
                "sector_id": {
                    "type": "integer"
                },
                "items": {
                    "type": "array",
                    "items": {
                        "type": "object",
                        "required": [
                            "commodity",
                            "quantity"
                        ],
                        "additionalProperties": false,
                        "properties": {
                            "commodity": {
                                "type": "string"
                            },
                            "quantity": {
                                "type": "integer"
                            }
                        }
                    }
                }
            }
        },
        "trade.cancel": {
            "$id": "ge://schema/trade.cancel.json",
            "$schema": "https://json-schema.org/draft/2020-12/schema",
            "type": "object",
            "properties": {
                "trade_id": {
                    "type": "integer",
                    "minimum": 1
                }
            },
            "required": [
                "trade_id"
            ],
            "additionalProperties": false
        },
        "trade.history": {
            "$id": "ge://schema/trade.history.json",
            "$schema": "https://json-schema.org/draft/2020-12/schema",
            "type": "object",
            "required": [],
            "additionalProperties": false,
            "properties": {
                "limit": {
                    "type": "integer",
                    "minimum": 1,
                    "maximum": 50
                },
                "cursor": {
                    "type": "string"
                }
            }
        },
        "trade.jettison": {
            "$id": "ge://schema/trade.jettison.json",
            "$schema": "https://json-schema.org/draft/2020-12/schema",
            "type": "object",
            "properties": {
                "commodity": {
                    "type": "string"
                },
                "quantity": {
                    "type": "integer",
                    "minimum": 1
                }
            },
            "required": [
                "commodity",
                "quantity"
            ],
            "additionalProperties": false
        },
        "trade.offer": {
            "$id": "ge://schema/trade.offer.json",
            "$schema": "https://json-schema.org/draft/2020-12/schema",
            "type": "object",
            "properties": {
                "trade_id": {
                    "type": "integer",
                    "minimum": 1
                }
            },
            "required": [
                "trade_id"
            ],
            "additionalProperties": false
        },
        "trade.port_info": {
            "$id": "ge://schema/trade.port_info.json",
            "$schema": "https://json-schema.org/draft/2020-12/schema",
            "type": "object",
            "properties": {},
            "additionalProperties": false
        },
        "trade.quote": {
            "$id": "ge://schema/trade.quote.json",
            "$schema": "https://json-schema.org/draft/2020-12/schema",
            "type": "object",
            "properties": {
                "port_id": {
                    "type": "integer"
                },
                "commodity": {
                    "type": "string"
                },
                "quantity": {
                    "type": "integer"
                }
            },
            "required": [
                "port_id",
                "commodity",
                "quantity"
            ],
            "additionalProperties": false
        },
        "trade.sell": {
            "$id": "ge://schema/trade.sell.json",
            "$schema": "https://json-schema.org/draft/2020-12/schema",
            "type": "object",
            "required": [
                "sector_id",
                "port_id",
                "items",
                "idempotency_key",
                "account"
            ],
            "additionalProperties": false,
            "properties": {
                "sector_id": {
                    "type": "integer"
                },
                "port_id": {
                    "type": "integer"
                },
                "idempotency_key": {
                    "type": "string"
                },
                "account": {
                    "type": "integer",
                    "enum": [
                        0,
                        1
                    ]
                },
                "items": {
                    "type": "array",
                    "items": {
                        "type": "object",
                        "required": [
                            "commodity",
                            "quantity"
                        ],
                        "additionalProperties": false,
                        "properties": {
                            "commodity": {
                                "type": "string"
                            },
                            "quantity": {
                                "type": "integer"
                            }
                        }
                    }
                }
            }
        }
    },
    "schema_blacklist": [],
    "pending_schema_requests": {
        "system.cmd_list": "c-de94a773",
        "admin.notice": "c-40d703bb",
        "admin.shutdown_warning": "c-3d1ef6ec",
        "auth.login": "c-31e2eb5c",
        "auth.logout": "c-53faa8db",
        "auth.mfa.totp.verify": "c-00516f51",
        "auth.register": "c-2be13dfc",
        "auth.refresh": "c-72c11ad8",
        "bank.balance": "c-59dada6c",
        "bank.deposit": "c-3759becc",
        "bank.history": "c-09093864",
        "bank.leaderboard": "c-c0779088",
        "bank.transfer": "c-f140542e",
        "bank.withdraw": "c-923a47b2",
        "bounty.list": "c-e3f32998",
        "bounty.post_federation": "c-775837ce",
        "bounty.post_hitlist": "c-4703c1c0",
        "bulk.execute": "c-83cd9be9",
        "fine.list": "c-b92d7f26",
        "fine.pay": "c-7dee6634",
        "insurance.policies.list": "c-3651e6ee",
        "insurance.policies.buy": "c-45507a2d",
        "insurance.claim.file": "c-b28ebd54",
        "chat.broadcast": "c-64f33e2d",
        "chat.history": "c-fbfafe4c",
        "chat.send": "c-e43de6eb",
        "citadel.build": "c-66588b51",
        "citadel.upgrade": "c-55e69fcd",
        "combat.attack": "c-4884000d",
        "combat.attack_planet": "c-4c803953",
        "combat.deploy_fighters": "c-8c63b1f0",
        "combat.deploy_mines": "c-2333fe31",
        "combat.lay_mines": "c-16511479",
        "combat.status": "c-86407d9a",
        "combat.sweep_mines": "c-64703f74",
        "deploy.fighters.list": "c-a247f3ea",
        "deploy.mines.list": "c-2976c4fd",
        "fighters.recall": "c-994feb5d",
        "mines.recall": "c-c288be27",
        "corp.balance": "c-08985ebd",
        "corp.create": "c-ebc47b25",
        "corp.deposit": "c-f9f39e14",
        "corp.dissolve": "c-df12afe0",
        "corp.invite": "c-106971ae",
        "corp.join": "c-4553846e",
        "corp.kick": "c-ae270b7a",
        "corp.leave": "c-63add012",
        "corp.list": "c-1fae7936",
        "corp.roster": "c-09c3f8a5",
        "corp.statement": "c-103aae48",
        "corp.status": "c-dd759fd8",
        "corp.transfer_ceo": "c-8dd7fafd",
        "corp.withdraw": "c-472345d0",
        "dock.status": "c-e4ac43e0",
        "hardware.buy": "c-707b88b0",
        "hardware.list": "c-f72a54f1",
        "mail.delete": "c-f781f9dc",
        "mail.inbox": "c-90f86876",
        "mail.read": "c-106641ca",
        "mail.send": "c-d9111af8",
        "move.autopilot.start": "c-34402cb5",
        "move.autopilot.status": "c-001a5aca",
        "move.autopilot.stop": "c-03589340",
        "move.describe_sector": "c-057371e1",
        "move.pathfind": "c-e064cb6c",
        "move.scan": "c-e6e532d4",
        "move.transwarp": "c-aa76e541",
        "move.warp": "c-cd79b85f",
        "nav.avoid.add": "c-b4675d27",
        "nav.avoid.list": "c-0975ef11",
        "nav.avoid.remove": "c-e0010d34",
        "nav.avoid.set": "c-db1e72c9",
        "nav.bookmark.add": "c-e714d7aa",
        "nav.bookmark.list": "c-789ce133",
        "nav.bookmark.remove": "c-7ec8366c",
        "nav.bookmark.set": "c-28f54f41",
        "news.get_feed": "c-4506e5f8",
        "news.mark_feed_read": "c-8f229151",
        "news.read": "c-8747a46f",
        "notes.list": "c-5b449546",
        "notice.ack": "c-0b00228b",
        "notice.list": "c-06fc0e21",
        "planet.create": "c-e8d2f818",
        "planet.deposit": "c-e9087fce",
        "planet.genesis": "c-1580bd75",
        "planet.genesis_create": "c-30514642",
        "planet.harvest": "c-fa442025",
        "planet.info": "c-db490a7c",
        "planet.land": "c-57b7f024",
        "planet.launch": "c-97f1709d",
        "planet.market.buy_order": "c-209f0153",
        "planet.market.sell": "c-82ccf856",
        "planet.rename": "c-1fbae5f7",
        "planet.transfer_ownership": "c-910376d9",
        "planet.withdraw": "c-e50f0764",
        "player.get_avoids": "c-d58bcc8c",
        "player.get_bookmarks": "c-c7db83a4",
        "player.get_notes": "c-bdc4391b",
        "player.get_prefs": "c-c91ec044",
        "player.get_settings": "c-85feb2a4",
        "player.get_subscriptions": "c-7a98c552",
        "player.get_topics": "c-c6236e38",
        "player.my_info": "c-31bfb36e",
        "player.rankings": "c-dc0b6057",
        "player.set_avoids": "c-34a5df9c",
        "player.set_bookmarks": "c-62f14e46",
        "player.set_prefs": "c-71476bf7",
        "player.set_settings": "c-4b3bf481",
        "player.set_subscriptions": "c-50072058",
        "player.set_topics": "c-f717edd1",
        "player.set_trade_account_preference": "c-ae635cb3",
        "port.describe": "c-1e2a0e73",
        "port.info": "c-54131020",
        "port.rob": "c-83ce411e",
        "port.status": "c-7e8e2303",
        "sector.info": "c-d9bd1777",
        "sector.scan": "c-560620a9",
        "sector.scan.density": "c-6f096c82",
        "sector.search": "c-75ff326d",
        "sector.set_beacon": "c-b93c8423",
        "session.disconnect": "c-0e380d04",
        "session.hello": "c-90dd7b41",
        "session.ping": "c-43dcbd2e",
        "player.ping": "c-e8d4342a",
        "sys.notice.create": "c-fa33c7c4",
        "system.disconnect": "c-3a99d3c9",
        "ship.claim": "c-5153b5bc",
        "ship.info": "c-b203d7d4",
        "ship.inspect": "c-34cff2b1",
        "ship.jettison": "c-09350049",
        "ship.list": "c-8e5b5b0b",
        "ship.rename": "c-76005ef9",
        "ship.repair": "c-dc5b2657",
        "ship.reregister": "c-98822df1",
        "ship.self_destruct": "c-91dcad53",
        "ship.sell": "c-9caf863e",
        "ship.status": "c-9cffac9f",
        "ship.transfer": "c-9867f927",
        "ship.transfer_cargo": "c-33b8eee4",
        "ship.upgrade": "c-123fc38c",
        "shipyard.list": "c-02df5cb5",
        "shipyard.sell": "c-092d9ab0",
        "shipyard.upgrade": "c-92b533d5",
        "stock.buy": "c-b05263eb",
        "stock.dividend.set": "c-8adef216",
        "stock.exchange.list_stocks": "c-55f0796f",
        "stock.exchange.orders.cancel": "c-b119ac2f",
        "stock.exchange.orders.create": "c-2ff6526a",
        "stock.ipo.register": "c-dab08c04",
        "stock.portfolio.list": "c-cf8f199f",
        "subscribe.add": "c-fa294ed4",
        "subscribe.catalog": "c-57fbccb2",
        "subscribe.list": "c-0c340935",
        "subscribe.remove": "c-459af611",
        "tavern.barcharts.get_prices_summary": "c-f39ad1a9",
        "tavern.deadpool.place_bet": "c-e868dac5",
        "tavern.dice.play": "c-9fddc722",
        "tavern.graffiti.post": "c-46387350",
        "tavern.highstakes.play": "c-795133e2",
        "tavern.loan.pay": "c-55547629",
        "tavern.loan.take": "c-a252eba5",
        "tavern.lottery.buy_ticket": "c-c0c9fc5f",
        "tavern.lottery.status": "c-9db807b7",
        "tavern.raffle.buy_ticket": "c-efb92e19",
        "tavern.round.buy": "c-f0205004",
        "tavern.rumour.get_hint": "c-ac6b510b",
        "tavern.trader.buy_password": "c-dc68c626",
        "trade.accept": "c-eec0eef4",
        "trade.buy": "c-cc59e3dc",
        "trade.cancel": "c-1a697025",
        "trade.history": "c-2a6244ec",
        "trade.jettison": "c-3e1a4c27",
        "trade.offer": "c-479cf505",
        "trade.port_info": "c-1fdcb8bf",
        "trade.quote": "c-201798fe",
        "trade.sell": "c-3d6e6f88"
    },
    "recent_sectors": [
        1
    ],
    "pending_commands": {},
    "port_trade_blacklist": [],
    "warp_blacklist": [],
    "current_path": [],
    "last_action_result": {
        "status": "ok",
        "command": "sector.info",
        "request_id": "c-0d2f7063",
        "response_type": "sector.info",
        "ts": "2026-01-11T13:58:17Z"
    },
    "last_quotes": {},
    "current_qa_objective": "test bounty hunting",
    "needs_bootstrap": false
}