{
    "session_id": "5759c6e97e6e72579d3db490338a7a5c",
    "player_info": {
        "player": {
            "player_id": 217,
            "current_sector": 2,
            "unread_news_count": 0,
            "session_token": "5759c6e97e6e72579d3db490338a7a5c",
            "id": 217,
            "username": "ai_qa_bot_004",
            "credits": "5000.00",
            "turns_remaining": 500,
            "sector": 2,
            "ship_id": 119,
            "corp_id": 0,
            "alignment": 1,
            "experience": 0
        }
    },
    "ship_info": {
        "id": 119,
        "name": "ai_qa_bot_004's ship",
        "type_id": 2,
        "holds": 10,
        "fighters": 1,
        "shields": 1,
        "onplanet": 0,
        "ported": 0,
        "cargo": []
    },
    "player_location_sector": 1,
    "sector_data": {
        "2": {
            "server_tick": 133200,
            "sector_id": 2,
            "name": "Fedspace 2",
            "beacon": "The Federation -- Do Not Dump!",
            "adjacent_sectors": [
                {
                    "to_sector": 1
                },
                {
                    "to_sector": 3
                },
                {
                    "to_sector": 7
                },
                {
                    "to_sector": 8
                },
                {
                    "to_sector": 9
                },
                {
                    "to_sector": 10
                },
                {
                    "to_sector": 432
                }
            ],
            "ships_present": [
                {
                    "ship_id": 88,
                    "name": "TestShip"
                },
                {
                    "ship_id": 119,
                    "name": "ai_qa_bot_004's ship"
                },
                {
                    "ship_id": 87,
                    "name": "TestShip"
                }
            ],
            "ports": [],
            "celestial_objects": [],
            "counts": {
                "fighters": 0,
                "mines": 0
            },
            "_last_refreshed": 1770064457.681207,
            "has_port": false,
            "adjacent": [
                {
                    "to_sector": 1
                },
                {
                    "to_sector": 3
                },
                {
                    "to_sector": 7
                },
                {
                    "to_sector": 8
                },
                {
                    "to_sector": 9
                },
                {
                    "to_sector": 10
                },
                {
                    "to_sector": 432
                }
            ]
        },
        "8": {
            "server_tick": 131281,
            "sector_id": 8,
            "name": "Fedspace 8",
            "beacon": "The Federation -- Do Not Dump!",
            "adjacent_sectors": [
                {
                    "to_sector": 2
                },
                {
                    "to_sector": 7
                },
                {
                    "to_sector": 9
                }
            ],
            "ships_present": [
                {
                    "ship_id": 121,
                    "name": "ai_qa_bot_006's ship"
                },
                {
                    "ship_id": 119,
                    "name": "ai_qa_bot_004's ship"
                }
            ],
            "ports": [],
            "celestial_objects": [],
            "counts": {
                "fighters": 0,
                "mines": 0
            },
            "_last_refreshed": 1770064265.264768,
            "has_port": false,
            "adjacent": [
                {
                    "to_sector": 2
                },
                {
                    "to_sector": 7
                },
                {
                    "to_sector": 9
                }
            ]
        },
        "9": {
            "server_tick": 131921,
            "sector_id": 9,
            "name": "Fedspace 9",
            "beacon": "The Federation -- Do Not Dump!",
            "adjacent_sectors": [
                {
                    "to_sector": 2
                },
                {
                    "to_sector": 8
                },
                {
                    "to_sector": 10
                }
            ],
            "ships_present": [
                {
                    "ship_id": 119,
                    "name": "ai_qa_bot_004's ship"
                }
            ],
            "ports": [],
            "celestial_objects": [],
            "counts": {
                "fighters": 0,
                "mines": 0
            },
            "_last_refreshed": 1770064329.394313,
            "has_port": false,
            "adjacent": [
                {
                    "to_sector": 2
                },
                {
                    "to_sector": 8
                },
                {
                    "to_sector": 10
                }
            ]
        },
        "10": {
            "server_tick": 132560,
            "sector_id": 10,
            "name": "Fedspace 10",
            "beacon": "The Federation -- Do Not Dump!",
            "adjacent_sectors": [
                {
                    "to_sector": 2
                },
                {
                    "to_sector": 9
                }
            ],
            "ships_present": [
                {
                    "ship_id": 119,
                    "name": "ai_qa_bot_004's ship"
                }
            ],
            "ports": [],
            "celestial_objects": [],
            "counts": {
                "fighters": 0,
                "mines": 0
            },
            "_last_refreshed": 1770064393.517511,
            "has_port": false,
            "adjacent": [
                {
                    "to_sector": 2
                },
                {
                    "to_sector": 9
                }
            ]
        },
        "1": {
            "server_tick": 180919,
            "sector_id": 1,
            "name": "Fedspace 1",
            "beacon": "The Federation -- Do Not Dump!",
            "adjacent_sectors": [
                {
                    "to_sector": 2
                },
                {
                    "to_sector": 3
                },
                {
                    "to_sector": 4
                },
                {
                    "to_sector": 5
                },
                {
                    "to_sector": 6
                },
                {
                    "to_sector": 7
                },
                {
                    "to_sector": 555
                }
            ],
            "ships_present": [
                {
                    "ship_id": 81,
                    "name": "Used Scout Marauder"
                },
                {
                    "ship_id": 82,
                    "name": "Used Scout Marauder"
                },
                {
                    "ship_id": 91,
                    "name": "TowedShip"
                },
                {
                    "ship_id": 95,
                    "name": "TowedShip"
                },
                {
                    "ship_id": 99,
                    "name": "TowedShip"
                },
                {
                    "ship_id": 89,
                    "name": "TestShip"
                },
                {
                    "ship_id": 93,
                    "name": "TowedShip"
                },
                {
                    "ship_id": 92,
                    "name": "TestShip"
                },
                {
                    "ship_id": 97,
                    "name": "TowedShip"
                },
                {
                    "ship_id": 101,
                    "name": "TowedShip"
                },
                {
                    "ship_id": 117,
                    "name": "ai_qa_bot_002's ship"
                },
                {
                    "ship_id": 121,
                    "name": "ai_qa_bot_006's ship"
                },
                {
                    "ship_id": 118,
                    "name": "ai_qa_bot_003's ship"
                },
                {
                    "ship_id": 123,
                    "name": "ai_qa_bot_008's ship"
                },
                {
                    "ship_id": 116,
                    "name": "ai_qa_bot_001's ship"
                },
                {
                    "ship_id": 119,
                    "name": "ai_qa_bot_004's ship"
                },
                {
                    "ship_id": 124,
                    "name": "ai_qa_bot_009's ship"
                },
                {
                    "ship_id": 122,
                    "name": "ai_qa_bot_007's ship"
                }
            ],
            "ports": [
                {
                    "port_id": 1,
                    "name": "Tavern Central",
                    "type": 10
                },
                {
                    "port_id": 2,
                    "name": "Trader Outpost",
                    "type": 1
                },
                {
                    "port_id": 9,
                    "name": "Stardock Prime",
                    "type": 9
                }
            ],
            "celestial_objects": [
                {
                    "planet_id": 7777,
                    "name": "Construction World",
                    "type": 1
                }
            ],
            "counts": {
                "fighters": 0,
                "mines": 0
            },
            "_last_refreshed": 1770069244.8632672,
            "has_port": true,
            "has_planet": true,
            "adjacent": [
                {
                    "to_sector": 2
                },
                {
                    "to_sector": 3
                },
                {
                    "to_sector": 4
                },
                {
                    "to_sector": 5
                },
                {
                    "to_sector": 6
                },
                {
                    "to_sector": 7
                },
                {
                    "to_sector": 555
                }
            ]
        }
    },
    "universe_map": {
        "2": {
            "is_explored": true,
            "has_port": false
        },
        "8": {
            "is_explored": true,
            "has_port": false
        },
        "9": {
            "is_explored": true,
            "has_port": false
        },
        "10": {
            "is_explored": true,
            "has_port": false
        },
        "1": {
            "is_explored": true,
            "has_port": true
        }
    },
    "port_info_by_sector": {
        "1": {
            "port_id": 1,
            "name": "Tavern Central",
            "class": null,
            "commodities": []
        }
    },
    "price_cache": {
        "1": {
            "buy": {
                "ORE": 0.0,
                "ORG": 0.0,
                "EQU": 0.0
            },
            "sell": {
                "ORE": 0.0,
                "ORG": 0.0,
                "EQU": 0.0
            }
        }
    },
    "bank_balance": 0,
    "command_retry_info": {
        "player.my_info": {
            "next_retry_time": 1770064137.4671543,
            "failures": 0
        },
        "ship.info": {
            "next_retry_time": 1770064141.3757365,
            "failures": 0
        },
        "sector.info": {
            "next_retry_time": 1770069248.8521652,
            "failures": 0
        },
        "move.warp": {
            "next_retry_time": 1770064462.6966784,
            "failures": 0
        },
        "trade.port_info": {
            "next_retry_time": 1770064526.8653126,
            "failures": 0
        },
        "trade.quote": {
            "next_retry_time": 1770069300.8113866,
            "failures": 0
        }
    },
    "strategy_plan": [
        "survey: port"
    ],
    "trade_successful": false,
    "q_table": {},
    "n_table": {},
    "command_schemas": {
        "admin.notice": {
            "$id": "ge://schema/admin.notice.json",
            "$schema": "https://json-schema.org/draft/2020-12/schema",
            "type": "object"
        },
        "admin.shutdown_warning": {
            "$id": "ge://schema/admin.shutdown_warning.json",
            "$schema": "https://json-schema.org/draft/2020-12/schema",
            "type": "object"
        },
        "auth.login": {
            "$id": "ge://schema/auth.login.json",
            "$schema": "https://json-schema.org/draft/2020-12/schema",
            "type": "object",
            "properties": {
                "username": {
                    "type": "string"
                },
                "passwd": {
                    "type": "string"
                }
            },
            "required": [
                "username",
                "passwd"
            ],
            "additionalProperties": false
        },
        "auth.logout": {
            "$id": "ge://schema/auth.logout.json",
            "$schema": "https://json-schema.org/draft/2020-12/schema",
            "type": "object",
            "properties": {},
            "additionalProperties": false
        },
        "auth.mfa.totp.verify": {
            "$id": "ge://schema/auth.mfa.totp.verify.json",
            "$schema": "https://json-schema.org/draft/2020-12/schema",
            "type": "object",
            "properties": {
                "code": {
                    "type": "string",
                    "pattern": "^[0-9]{6}$"
                }
            },
            "required": [
                "code"
            ],
            "additionalProperties": false
        },
        "auth.register": {
            "$id": "ge://schema/auth.register.json",
            "$schema": "https://json-schema.org/draft/2020-12/schema",
            "type": "object",
            "required": [
                "username",
                "passwd"
            ],
            "additionalProperties": false,
            "properties": {
                "username": {
                    "type": "string"
                },
                "passwd": {
                    "type": "string"
                },
                "ship_name": {
                    "type": "string"
                },
                "ui_locale": {
                    "type": "string"
                },
                "ui_timezone": {
                    "type": "string"
                }
            }
        },
        "auth.refresh": {
            "$id": "ge://schema/auth.refresh.json",
            "$schema": "https://json-schema.org/draft/2020-12/schema",
            "type": "object",
            "properties": {},
            "additionalProperties": false
        },
        "auth.change_password": {
            "$id": "ge://schema/placeholder.json",
            "$comment": "Not yet implemented",
            "type": "object"
        },
        "bank.balance": {
            "$id": "ge://schema/bank.balance.json",
            "$schema": "https://json-schema.org/draft/2020-12/schema",
            "type": "object",
            "properties": {},
            "required": [],
            "additionalProperties": false
        },
        "bank.deposit": {
            "$id": "ge://schema/placeholder.json",
            "$comment": "Not yet implemented",
            "type": "object"
        },
        "bank.history": {
            "$id": "ge://schema/bank.history.json",
            "$schema": "https://json-schema.org/draft/2020-12/schema",
            "type": "object",
            "required": [],
            "additionalProperties": false,
            "properties": {
                "limit": {
                    "type": "integer",
                    "minimum": 1,
                    "maximum": 50
                },
                "cursor": {
                    "type": "string"
                },
                "tx_type": {
                    "type": "string",
                    "enum": [
                        "DEPOSIT",
                        "WITHDRAWAL",
                        "TRANSFER",
                        "INTEREST",
                        "FEE",
                        "WIRE",
                        "TAX",
                        "TRADE_BUY_FEE",
                        "TRADE_SELL_FEE",
                        "WITHDRAWAL_FEE",
                        "ADJUSTMENT"
                    ]
                },
                "start_date": {
                    "type": "integer"
                },
                "end_date": {
                    "type": "integer"
                },
                "min_amount": {
                    "type": "integer",
                    "minimum": 0
                },
                "max_amount": {
                    "type": "integer",
                    "minimum": 0
                }
            }
        },
        "bank.leaderboard": {
            "$id": "ge://schema/bank.leaderboard.json",
            "$schema": "https://json-schema.org/draft/2020-12/schema",
            "type": "object",
            "properties": {
                "limit": {
                    "type": "integer",
                    "minimum": 1,
                    "maximum": 100
                }
            },
            "required": [],
            "additionalProperties": false
        },
        "bank.transfer": {
            "$id": "ge://schema/placeholder.json",
            "$comment": "Not yet implemented",
            "type": "object"
        },
        "bank.withdraw": {
            "$id": "ge://schema/placeholder.json",
            "$comment": "Not yet implemented",
            "type": "object"
        },
        "bounty.list": {
            "$id": "ge://schema/placeholder.json",
            "$comment": "Not yet implemented",
            "type": "object"
        },
        "bounty.post_federation": {
            "$id": "ge://schema/placeholder.json",
            "$comment": "Not yet implemented",
            "type": "object"
        },
        "bounty.post_hitlist": {
            "$id": "ge://schema/placeholder.json",
            "$comment": "Not yet implemented",
            "type": "object"
        },
        "bulk.execute": {
            "$id": "ge://schema/bulk.execute.json",
            "$schema": "https://json-schema.org/draft/2020-12/schema",
            "type": "object",
            "properties": {
                "commands": {
                    "type": "array",
                    "minItems": 1
                }
            },
            "required": [
                "commands"
            ],
            "additionalProperties": false
        },
        "fine.list": {
            "$id": "ge://schema/fine.list.json",
            "$schema": "https://json-schema.org/draft/2020-12/schema",
            "type": "object",
            "properties": {},
            "required": [],
            "additionalProperties": false
        },
        "fine.pay": {
            "$id": "ge://schema/fine.pay.json",
            "$schema": "https://json-schema.org/draft/2020-12/schema",
            "type": "object",
            "properties": {
                "fine_id": {
                    "type": "integer"
                },
                "amount": {
                    "type": "integer"
                }
            },
            "required": [
                "fine_id"
            ],
            "additionalProperties": false
        },
        "insurance.policies.list": {
            "$id": "ge://schema/insurance.policies.list.json",
            "$schema": "https://json-schema.org/draft/2020-12/schema",
            "type": "object",
            "properties": {},
            "required": [],
            "additionalProperties": false
        },
        "insurance.policies.buy": {
            "$id": "ge://schema/insurance.policies.buy.json",
            "$schema": "https://json-schema.org/draft/2020-12/schema",
            "type": "object",
            "properties": {
                "subject_type": {
                    "type": "string",
                    "enum": [
                        "ship",
                        "cargo",
                        "planet"
                    ]
                },
                "subject_id": {
                    "type": "integer"
                },
                "duration": {
                    "type": "integer"
                },
                "premium": {
                    "type": "integer"
                }
            },
            "required": [
                "subject_type",
                "subject_id",
                "duration",
                "premium"
            ],
            "additionalProperties": false
        },
        "insurance.claim.file": {
            "$id": "ge://schema/insurance.claim.file.json",
            "$schema": "https://json-schema.org/draft/2020-12/schema",
            "type": "object",
            "properties": {
                "policy_id": {
                    "type": "integer"
                },
                "incident_description": {
                    "type": "string"
                }
            },
            "required": [
                "policy_id",
                "incident_description"
            ],
            "additionalProperties": false
        },
        "chat.broadcast": {
            "$id": "ge://schema/chat.broadcast.json",
            "$schema": "https://json-schema.org/draft/2020-12/schema",
            "type": "object",
            "properties": {
                "message": {
                    "type": "string",
                    "minLength": 1
                }
            },
            "required": [
                "message"
            ],
            "additionalProperties": false
        },
        "chat.history": {
            "$id": "ge://schema/chat.history.json",
            "$schema": "https://json-schema.org/draft/2020-12/schema",
            "type": "object",
            "properties": {
                "channel": {
                    "type": "string"
                },
                "limit": {
                    "type": "integer",
                    "minimum": 1,
                    "maximum": 100
                }
            },
            "additionalProperties": false
        },
        "chat.send": {
            "$id": "ge://schema/chat.send.json",
            "$schema": "https://json-schema.org/draft/2020-12/schema",
            "type": "object",
            "properties": {
                "channel": {
                    "type": "string"
                },
                "message": {
                    "type": "string",
                    "minLength": 1
                }
            },
            "required": [
                "channel",
                "message"
            ],
            "additionalProperties": false
        },
        "citadel.build": {
            "$id": "ge://schema/citadel.build.json",
            "$schema": "https://json-schema.org/draft/2020-12/schema",
            "type": "object",
            "properties": {
                "sector_id": {
                    "type": "integer",
                    "minimum": 1
                }
            },
            "required": [
                "sector_id"
            ],
            "additionalProperties": false
        },
        "citadel.upgrade": {
            "$id": "ge://schema/citadel.upgrade.json",
            "$schema": "https://json-schema.org/draft/2020-12/schema",
            "type": "object",
            "properties": {
                "citadel_id": {
                    "type": "integer",
                    "minimum": 1
                }
            },
            "required": [
                "citadel_id"
            ],
            "additionalProperties": false
        },
        "combat.attack": {
            "$id": "ge://schema/combat.attack.json",
            "$schema": "https://json-schema.org/draft/2020-12/schema",
            "type": "object",
            "properties": {
                "target_ship_id": {
                    "type": "integer",
                    "minimum": 1
                }
            },
            "required": [
                "target_ship_id"
            ],
            "additionalProperties": false
        },
        "combat.attack_planet": {
            "$id": "ge://schema/placeholder.json",
            "$comment": "Not yet implemented",
            "type": "object"
        },
        "combat.deploy_fighters": {
            "$id": "ge://schema/combat.deploy_fighters.json",
            "$schema": "https://json-schema.org/draft/2020-12/schema",
            "type": "object",
            "required": [
                "amount",
                "offense"
            ],
            "additionalProperties": false,
            "properties": {
                "amount": {
                    "type": "integer"
                },
                "offense": {
                    "type": "integer"
                },
                "corporation_id": {
                    "type": "integer"
                }
            }
        },
        "combat.deploy_mines": {
            "$id": "ge://schema/combat.deploy_mines.json",
            "$schema": "https://json-schema.org/draft/2020-12/schema",
            "type": "object",
            "required": [
                "amount",
                "offense"
            ],
            "additionalProperties": false,
            "properties": {
                "amount": {
                    "type": "integer"
                },
                "offense": {
                    "type": "integer"
                },
                "corporation_id": {
                    "type": "integer"
                },
                "mine_type": {
                    "type": "integer"
                }
            }
        },
        "combat.lay_mines": {
            "$id": "ge://schema/combat.lay_mines.json",
            "$schema": "https://json-schema.org/draft/2020-12/schema",
            "type": "object",
            "properties": {
                "quantity": {
                    "type": "integer",
                    "minimum": 1
                }
            },
            "required": [
                "quantity"
            ],
            "additionalProperties": false
        },
        "combat.status": {
            "$id": "ge://schema/combat.status.json",
            "$schema": "https://json-schema.org/draft/2020-12/schema",
            "type": "object",
            "properties": {},
            "additionalProperties": false
        },
        "combat.sweep_mines": {
            "$id": "ge://schema/combat.sweep_mines.json",
            "$schema": "https://json-schema.org/draft/2020-12/schema",
            "type": "object",
            "properties": {},
            "additionalProperties": false
        },
        "deploy.fighters.list": {
            "$id": "ge://schema/deploy.fighters.list.json",
            "$schema": "https://json-schema.org/draft/2020-12/schema",
            "type": "object",
            "properties": {},
            "required": [],
            "additionalProperties": false
        },
        "deploy.mines.list": {
            "$id": "ge://schema/deploy.mines.list.json",
            "$schema": "https://json-schema.org/draft/2020-12/schema",
            "type": "object",
            "properties": {},
            "required": [],
            "additionalProperties": false
        },
        "fighters.recall": {
            "$id": "ge://schema/fighters.recall.json",
            "$schema": "https://json-schema.org/draft/2020-12/schema",
            "type": "object",
            "required": [
                "sector_id",
                "asset_id"
            ],
            "additionalProperties": false,
            "properties": {
                "sector_id": {
                    "type": "integer"
                },
                "asset_id": {
                    "type": "integer"
                }
            }
        },
        "mines.recall": {
            "$id": "ge://schema/mines.recall.json",
            "$schema": "https://json-schema.org/draft/2020-12/schema",
            "type": "object",
            "required": [
                "sector_id",
                "asset_id"
            ],
            "additionalProperties": false,
            "properties": {
                "sector_id": {
                    "type": "integer"
                },
                "asset_id": {
                    "type": "integer"
                }
            }
        },
        "corp.balance": {
            "$id": "ge://schema/placeholder.json",
            "$comment": "Not yet implemented",
            "type": "object"
        },
        "corp.create": {
            "$id": "ge://schema/placeholder.json",
            "$comment": "Not yet implemented",
            "type": "object"
        },
        "corp.deposit": {
            "$id": "ge://schema/placeholder.json",
            "$comment": "Not yet implemented",
            "type": "object"
        },
        "corp.dissolve": {
            "$id": "ge://schema/placeholder.json",
            "$comment": "Not yet implemented",
            "type": "object"
        },
        "corp.invite": {
            "$id": "ge://schema/placeholder.json",
            "$comment": "Not yet implemented",
            "type": "object"
        },
        "corp.join": {
            "$id": "ge://schema/placeholder.json",
            "$comment": "Not yet implemented",
            "type": "object"
        },
        "corp.kick": {
            "$id": "ge://schema/placeholder.json",
            "$comment": "Not yet implemented",
            "type": "object"
        },
        "corp.leave": {
            "$id": "ge://schema/placeholder.json",
            "$comment": "Not yet implemented",
            "type": "object"
        },
        "corp.list": {
            "$id": "ge://schema/placeholder.json",
            "$comment": "Not yet implemented",
            "type": "object"
        },
        "corp.roster": {
            "$id": "ge://schema/placeholder.json",
            "$comment": "Not yet implemented",
            "type": "object"
        },
        "corp.statement": {
            "$id": "ge://schema/placeholder.json",
            "$comment": "Not yet implemented",
            "type": "object"
        },
        "corp.status": {
            "$id": "ge://schema/placeholder.json",
            "$comment": "Not yet implemented",
            "type": "object"
        },
        "corp.transfer_ceo": {
            "$id": "ge://schema/placeholder.json",
            "$comment": "Not yet implemented",
            "type": "object"
        },
        "corp.withdraw": {
            "$id": "ge://schema/placeholder.json",
            "$comment": "Not yet implemented",
            "type": "object"
        },
        "dock.status": {
            "$id": "ge://schema/placeholder.json",
            "$comment": "Not yet implemented",
            "type": "object"
        },
        "hardware.buy": {
            "$id": "ge://schema/hardware.buy.json",
            "$schema": "https://json-schema.org/draft/2020-12/schema",
            "type": "object",
            "properties": {
                "code": {
                    "type": "string"
                },
                "quantity": {
                    "type": "integer",
                    "minimum": 1
                },
                "idempotency_key": {
                    "type": "string"
                }
            },
            "required": [
                "code",
                "quantity"
            ],
            "additionalProperties": false
        },
        "hardware.list": {
            "$id": "ge://schema/hardware.list.json",
            "$schema": "https://json-schema.org/draft/2020-12/schema",
            "type": "object",
            "properties": {},
            "required": [],
            "additionalProperties": false
        },
        "mail.delete": {
            "$id": "ge://schema/mail.delete.json",
            "$schema": "https://json-schema.org/draft/2020-12/schema",
            "type": "object",
            "properties": {
                "mail_id": {
                    "type": "integer",
                    "minimum": 1
                }
            },
            "required": [
                "mail_id"
            ],
            "additionalProperties": false
        },
        "mail.inbox": {
            "$id": "ge://schema/mail.inbox.json",
            "$schema": "https://json-schema.org/draft/2020-12/schema",
            "type": "object",
            "properties": {},
            "required": [],
            "additionalProperties": false
        },
        "mail.read": {
            "$id": "ge://schema/mail.read.json",
            "$schema": "https://json-schema.org/draft/2020-12/schema",
            "type": "object",
            "required": [
                "mail_id"
            ],
            "additionalProperties": false,
            "properties": {
                "mail_id": {
                    "type": "integer"
                }
            }
        },
        "mail.send": {
            "$id": "ge://schema/mail.send.json",
            "$schema": "https://json-schema.org/draft/2020-12/schema",
            "type": "object",
            "properties": {
                "to_player_name": {
                    "type": "string"
                },
                "subject": {
                    "type": "string"
                },
                "body": {
                    "type": "string"
                }
            },
            "required": [
                "to_player_name",
                "subject",
                "body"
            ],
            "additionalProperties": false
        },
        "move.autopilot.start": {
            "$id": "ge://schema/move.autopilot.start.json",
            "$schema": "https://json-schema.org/draft/2020-12/schema",
            "type": "object",
            "properties": {
                "to_sector_id": {
                    "type": "integer",
                    "minimum": 1
                }
            },
            "required": [
                "to_sector_id"
            ],
            "additionalProperties": false
        },
        "move.autopilot.status": {
            "$id": "ge://schema/move.autopilot.status.json",
            "$schema": "https://json-schema.org/draft/2020-12/schema",
            "type": "object",
            "properties": {},
            "required": [],
            "additionalProperties": false
        },
        "move.autopilot.stop": {
            "$id": "ge://schema/move.autopilot.stop.json",
            "$schema": "https://json-schema.org/draft/2020-12/schema",
            "type": "object",
            "properties": {},
            "additionalProperties": false
        },
        "move.describe_sector": {
            "$id": "ge://schema/move.describe_sector.json",
            "$schema": "https://json-schema.org/draft/2020-12/schema",
            "type": "object",
            "properties": {
                "sector_id": {
                    "type": "integer",
                    "minimum": 1
                }
            },
            "required": [
                "sector_id"
            ],
            "additionalProperties": false
        },
        "move.pathfind": {
            "$id": "ge://schema/move.pathfind.json",
            "$schema": "https://json-schema.org/draft/2020-12/schema",
            "type": "object",
            "properties": {
                "from_sector_id": {
                    "type": "integer",
                    "minimum": 1
                },
                "to_sector_id": {
                    "type": "integer",
                    "minimum": 1
                }
            },
            "required": [
                "from_sector_id",
                "to_sector_id"
            ],
            "additionalProperties": false
        },
        "move.scan": {
            "$id": "ge://schema/move.scan.json",
            "$schema": "https://json-schema.org/draft/2020-12/schema",
            "type": "object",
            "properties": {}
        },
        "move.transwarp": {
            "$id": "ge://schema/placeholder.json",
            "$comment": "Not yet implemented",
            "type": "object"
        },
        "move.warp": {
            "$id": "ge://schema/move_warp.json",
            "$schema": "https://json-schema.org/draft/2020-12/schema",
            "type": "object",
            "properties": {
                "to_sector_id": {
                    "type": "integer"
                }
            },
            "required": [
                "to_sector_id"
            ],
            "additionalProperties": false
        },
        "nav.avoid.add": {
            "$id": "ge://schema/placeholder.json",
            "$comment": "Not yet implemented",
            "type": "object"
        },
        "nav.avoid.list": {
            "$id": "ge://schema/placeholder.json",
            "$comment": "Not yet implemented",
            "type": "object"
        },
        "nav.avoid.remove": {
            "$id": "ge://schema/placeholder.json",
            "$comment": "Not yet implemented",
            "type": "object"
        },
        "nav.avoid.set": {
            "$id": "ge://schema/placeholder.json",
            "$comment": "Not yet implemented",
            "type": "object"
        },
        "nav.bookmark.add": {
            "$id": "ge://schema/placeholder.json",
            "$comment": "Not yet implemented",
            "type": "object"
        },
        "nav.bookmark.list": {
            "$id": "ge://schema/placeholder.json",
            "$comment": "Not yet implemented",
            "type": "object"
        },
        "nav.bookmark.remove": {
            "$id": "ge://schema/placeholder.json",
            "$comment": "Not yet implemented",
            "type": "object"
        },
        "nav.bookmark.set": {
            "$id": "ge://schema/placeholder.json",
            "$comment": "Not yet implemented",
            "type": "object"
        },
        "news.get_feed": {
            "$id": "ge://schema/placeholder.json",
            "$comment": "Not yet implemented",
            "type": "object"
        },
        "news.mark_feed_read": {
            "$id": "ge://schema/placeholder.json",
            "$comment": "Not yet implemented",
            "type": "object"
        },
        "news.read": {
            "$id": "ge://schema/news.read.json",
            "$schema": "https://json-schema.org/draft/2020-12/schema",
            "type": "object",
            "properties": {},
            "required": [],
            "additionalProperties": false
        },
        "notes.delete": {
            "$id": "ge://schema/placeholder.json",
            "$comment": "Not yet implemented",
            "type": "object"
        },
        "notes.list": {
            "$id": "ge://schema/placeholder.json",
            "$comment": "Not yet implemented",
            "type": "object"
        },
        "notes.set": {
            "$id": "ge://schema/placeholder.json",
            "$comment": "Not yet implemented",
            "type": "object"
        },
        "notice.ack": {
            "$id": "ge://schema/notice.ack.json",
            "$schema": "https://json-schema.org/draft/2020-12/schema",
            "type": "object",
            "properties": {
                "notice_id": {
                    "type": "integer"
                }
            },
            "required": [
                "notice_id"
            ],
            "additionalProperties": false
        },
        "notice.list": {
            "$id": "ge://schema/notice.list.json",
            "$schema": "https://json-schema.org/draft/2020-12/schema",
            "type": "object",
            "properties": {},
            "required": [],
            "additionalProperties": false
        },
        "planet.create": {
            "$id": "ge://schema/planet.genesis_create.json",
            "$schema": "https://json-schema.org/draft/2020-12/schema",
            "type": "object",
            "properties": {
                "sector_id": {
                    "type": "integer"
                },
                "name": {
                    "type": "string"
                },
                "owner_entity_type": {
                    "type": "string",
                    "enum": [
                        "player",
                        "corporation"
                    ]
                },
                "idempotency_key": {
                    "type": "string"
                }
            },
            "required": [
                "sector_id",
                "name",
                "owner_entity_type"
            ],
            "additionalProperties": false
        },
        "planet.deposit": {
            "$id": "ge://schema/planet.deposit.json",
            "$schema": "https://json-schema.org/draft/2020-12/schema",
            "type": "object",
            "properties": {
                "planet_id": {
                    "type": "integer",
                    "minimum": 1
                },
                "commodity": {
                    "type": "string"
                },
                "quantity": {
                    "type": "integer",
                    "minimum": 1
                }
            },
            "required": [
                "planet_id",
                "commodity",
                "quantity"
            ],
            "additionalProperties": false
        },
        "planet.genesis": {
            "$id": "ge://schema/planet.genesis.json",
            "$schema": "https://json-schema.org/draft/2020-12/schema",
            "type": "object",
            "properties": {
                "name": {
                    "type": "string",
                    "minLength": 1
                }
            },
            "required": [
                "name"
            ],
            "additionalProperties": false
        },
        "planet.genesis_create": {
            "$id": "ge://schema/planet.genesis_create.json",
            "$schema": "https://json-schema.org/draft/2020-12/schema",
            "type": "object",
            "properties": {
                "sector_id": {
                    "type": "integer"
                },
                "name": {
                    "type": "string"
                },
                "owner_entity_type": {
                    "type": "string",
                    "enum": [
                        "player",
                        "corporation"
                    ]
                },
                "idempotency_key": {
                    "type": "string"
                }
            },
            "required": [
                "sector_id",
                "name",
                "owner_entity_type"
            ],
            "additionalProperties": false
        },
        "planet.harvest": {
            "$id": "ge://schema/planet.harvest.json",
            "$schema": "https://json-schema.org/draft/2020-12/schema",
            "type": "object",
            "properties": {
                "planet_id": {
                    "type": "integer",
                    "minimum": 1
                }
            },
            "required": [
                "planet_id"
            ],
            "additionalProperties": false
        },
        "planet.info": {
            "$id": "ge://schema/planet.info.json",
            "$schema": "https://json-schema.org/draft/2020-12/schema",
            "type": "object",
            "properties": {
                "planet_id": {
                    "type": "integer",
                    "minimum": 1
                }
            },
            "required": [
                "planet_id"
            ],
            "additionalProperties": false
        },
        "planet.land": {
            "$id": "ge://schema/planet.land.json",
            "$schema": "https://json-schema.org/draft/2020-12/schema",
            "type": "object",
            "properties": {
                "planet_id": {
                    "type": "integer",
                    "minimum": 1
                }
            },
            "required": [
                "planet_id"
            ],
            "additionalProperties": false
        },
        "planet.launch": {
            "$id": "ge://schema/planet.launch.json",
            "$schema": "https://json-schema.org/draft/2020-12/schema",
            "type": "object",
            "properties": {},
            "additionalProperties": false
        },
        "planet.market.buy_order": {
            "$id": "ge://schema/placeholder.json",
            "$comment": "Not yet implemented",
            "type": "object"
        },
        "planet.market.sell": {
            "$id": "ge://schema/placeholder.json",
            "$comment": "Not yet implemented",
            "type": "object"
        },
        "planet.rename": {
            "$id": "ge://schema/planet.rename.json",
            "$schema": "https://json-schema.org/draft/2020-12/schema",
            "type": "object",
            "properties": {
                "planet_id": {
                    "type": "integer",
                    "minimum": 1
                },
                "name": {
                    "type": "string",
                    "minLength": 1
                }
            },
            "required": [
                "planet_id",
                "name"
            ],
            "additionalProperties": false
        },
        "planet.transfer_ownership": {
            "$id": "ge://schema/planet.transfer_ownership.json",
            "$schema": "https://json-schema.org/draft/2020-12/schema",
            "type": "object",
            "properties": {
                "planet_id": {
                    "type": "integer",
                    "minimum": 1
                },
                "new_owner_id": {
                    "type": "integer",
                    "minimum": 1
                }
            },
            "required": [
                "planet_id",
                "new_owner_id"
            ],
            "additionalProperties": false
        },
        "planet.withdraw": {
            "$id": "ge://schema/planet.withdraw.json",
            "$schema": "https://json-schema.org/draft/2020-12/schema",
            "type": "object",
            "properties": {
                "planet_id": {
                    "type": "integer",
                    "minimum": 1
                },
                "commodity": {
                    "type": "string"
                },
                "quantity": {
                    "type": "integer",
                    "minimum": 1
                }
            },
            "required": [
                "planet_id",
                "commodity",
                "quantity"
            ],
            "additionalProperties": false
        },
        "sysop.config.list": {
            "$id": "ge://schema/placeholder.json",
            "$comment": "Not yet implemented",
            "type": "object"
        },
        "sysop.config.get": {
            "$id": "ge://schema/placeholder.json",
            "$comment": "Not yet implemented",
            "type": "object"
        },
        "sysop.config.set": {
            "$id": "ge://schema/placeholder.json",
            "$comment": "Not yet implemented",
            "type": "object"
        },
        "sysop.config.history": {
            "$id": "ge://schema/placeholder.json",
            "$comment": "Not yet implemented",
            "type": "object"
        },
        "sysop.players.search": {
            "$id": "ge://schema/placeholder.json",
            "$comment": "Not yet implemented",
            "type": "object"
        },
        "sysop.player.get": {
            "$id": "ge://schema/placeholder.json",
            "$comment": "Not yet implemented",
            "type": "object"
        },
        "sysop.player.kick": {
            "$id": "ge://schema/placeholder.json",
            "$comment": "Not yet implemented",
            "type": "object"
        },
        "sysop.player.sessions.get": {
            "$id": "ge://schema/placeholder.json",
            "$comment": "Not yet implemented",
            "type": "object"
        },
        "sysop.universe.summary": {
            "$id": "ge://schema/placeholder.json",
            "$comment": "Not yet implemented",
            "type": "object"
        },
        "sysop.engine_status.get": {
            "$id": "ge://schema/placeholder.json",
            "$comment": "Not yet implemented",
            "type": "object"
        },
        "sysop.jobs.list": {
            "$id": "ge://schema/placeholder.json",
            "$comment": "Not yet implemented",
            "type": "object"
        },
        "sysop.jobs.get": {
            "$id": "ge://schema/placeholder.json",
            "$comment": "Not yet implemented",
            "type": "object"
        },
        "sysop.jobs.retry": {
            "$id": "ge://schema/placeholder.json",
            "$comment": "Not yet implemented",
            "type": "object"
        },
        "sysop.jobs.cancel": {
            "$id": "ge://schema/placeholder.json",
            "$comment": "Not yet implemented",
            "type": "object"
        },
        "sysop.notice.create": {
            "$id": "ge://schema/placeholder.json",
            "$comment": "Not yet implemented",
            "type": "object"
        },
        "sysop.notice.delete": {
            "$id": "ge://schema/placeholder.json",
            "$comment": "Not yet implemented",
            "type": "object"
        },
        "sysop.broadcast.send": {
            "$id": "ge://schema/placeholder.json",
            "$comment": "Not yet implemented",
            "type": "object"
        },
        "sysop.logs.tail": {
            "$id": "ge://schema/placeholder.json",
            "$comment": "Not yet implemented",
            "type": "object"
        },
        "sysop.logs.clear": {
            "$id": "ge://schema/placeholder.json",
            "$comment": "Not yet implemented",
            "type": "object"
        },
        "player.get_avoids": {
            "$id": "ge://schema/placeholder.json",
            "$comment": "Not yet implemented",
            "type": "object"
        },
        "player.get_bookmarks": {
            "$id": "ge://schema/placeholder.json",
            "$comment": "Not yet implemented",
            "type": "object"
        },
        "player.get_notes": {
            "$id": "ge://schema/placeholder.json",
            "$comment": "Not yet implemented",
            "type": "object"
        },
        "player.get_prefs": {
            "$id": "ge://schema/placeholder.json",
            "$comment": "Not yet implemented",
            "type": "object"
        },
        "player.get_settings": {
            "$id": "ge://schema/placeholder.json",
            "$comment": "Not yet implemented",
            "type": "object"
        },
        "player.get_subscriptions": {
            "$id": "ge://schema/placeholder.json",
            "$comment": "Not yet implemented",
            "type": "object"
        },
        "player.get_topics": {
            "$id": "ge://schema/placeholder.json",
            "$comment": "Not yet implemented",
            "type": "object"
        },
        "player.my_info": {
            "$id": "ge://schema/player.my_info.json",
            "$schema": "https://json-schema.org/draft/2020-12/schema",
            "type": "object",
            "properties": {},
            "required": [],
            "additionalProperties": false
        },
        "player.rankings": {
            "$id": "ge://schema/placeholder.json",
            "$comment": "Not yet implemented",
            "type": "object"
        },
        "player.computer.recommend_routes": {
            "$id": "ge://schema/player.computer.recommend_routes.json",
            "type": "object",
            "properties": {
                "max_hops_between": {
                    "type": "integer",
                    "default": 10
                },
                "max_hops_from_player": {
                    "type": "integer",
                    "default": 20
                },
                "require_two_way": {
                    "type": "boolean",
                    "default": false
                },
                "limit": {
                    "type": "integer",
                    "default": 10
                }
            }
        },
        "player.set_avoids": {
            "$id": "ge://schema/placeholder.json",
            "$comment": "Not yet implemented",
            "type": "object"
        },
        "player.set_bookmarks": {
            "$id": "ge://schema/placeholder.json",
            "$comment": "Not yet implemented",
            "type": "object"
        },
        "player.set_prefs": {
            "$id": "ge://schema/placeholder.json",
            "$comment": "Not yet implemented",
            "type": "object"
        },
        "player.set_settings": {
            "$id": "ge://schema/placeholder.json",
            "$comment": "Not yet implemented",
            "type": "object"
        },
        "player.set_subscriptions": {
            "$id": "ge://schema/placeholder.json",
            "$comment": "Not yet implemented",
            "type": "object"
        },
        "player.set_topics": {
            "$id": "ge://schema/placeholder.json",
            "$comment": "Not yet implemented",
            "type": "object"
        },
        "player.set_trade_account_preference": {
            "$id": "ge://schema/player.set_trade_account_preference.json",
            "$schema": "https://json-schema.org/draft/2020-12/schema",
            "type": "object",
            "properties": {
                "preference": {
                    "type": "integer",
                    "enum": [
                        0,
                        1
                    ]
                }
            },
            "required": [
                "preference"
            ],
            "additionalProperties": false
        },
        "port.describe": {
            "$id": "ge://schema/port.describe.json",
            "$schema": "https://json-schema.org/draft/2020-12/schema",
            "type": "object",
            "properties": {
                "port_id": {
                    "type": "integer"
                },
                "sector_id": {
                    "type": "integer"
                }
            },
            "anyOf": [
                {
                    "required": [
                        "port_id"
                    ]
                },
                {
                    "required": [
                        "sector_id"
                    ]
                }
            ],
            "additionalProperties": false
        },
        "port.info": {
            "$id": "ge://schema/port.info.json",
            "$schema": "https://json-schema.org/draft/2020-12/schema",
            "type": "object",
            "properties": {},
            "additionalProperties": false
        },
        "port.rob": {
            "$id": "ge://schema/port.rob.json",
            "$schema": "https://json-schema.org/draft/2020-12/schema",
            "type": "object",
            "properties": {
                "sector_id": {
                    "type": "integer"
                },
                "port_id": {
                    "type": "integer"
                },
                "mode": {
                    "type": "string",
                    "enum": [
                        "credits",
                        "goods"
                    ]
                },
                "commodity": {
                    "type": "string"
                },
                "amount": {
                    "type": "integer",
                    "minimum": 1
                },
                "idempotency_key": {
                    "type": "string"
                }
            },
            "required": [
                "sector_id",
                "port_id",
                "mode",
                "idempotency_key"
            ],
            "additionalProperties": false
        },
        "port.status": {
            "$id": "ge://schema/port.status.json",
            "$schema": "https://json-schema.org/draft/2020-12/schema",
            "type": "object",
            "properties": {
                "port_id": {
                    "type": "integer"
                },
                "sector_id": {
                    "type": "integer"
                }
            },
            "anyOf": [
                {
                    "required": [
                        "port_id"
                    ]
                },
                {
                    "required": [
                        "sector_id"
                    ]
                }
            ],
            "additionalProperties": false
        },
        "s2s.planet.genesis": {
            "$id": "ge://schema/placeholder.json",
            "$comment": "Not yet implemented",
            "type": "object"
        },
        "s2s.planet_genesis": {
            "$id": "ge://schema/placeholder.json",
            "$comment": "Not yet implemented",
            "type": "object"
        },
        "sector.info": {
            "$id": "ge://schema/sector.info.json",
            "$schema": "https://json-schema.org/draft/2020-12/schema",
            "type": "object",
            "properties": {
                "sector_id": {
                    "type": "integer"
                }
            },
            "required": [],
            "additionalProperties": false
        },
        "sector.mine_disrupt": {
            "$id": "ge://schema/placeholder.json",
            "$comment": "Not yet implemented",
            "type": "object"
        },
        "sector.scan": {
            "$id": "ge://schema/sector.scan.json",
            "$schema": "https://json-schema.org/draft/2020-12/schema",
            "type": "object",
            "properties": {},
            "additionalProperties": false
        },
        "sector.scan.density": {
            "$id": "ge://schema/sector.scan.density.json",
            "$schema": "https://json-schema.org/draft/2020-12/schema",
            "type": "object",
            "properties": {},
            "additionalProperties": false
        },
        "sector.search": {
            "$id": "ge://schema/sector.search.json",
            "$schema": "https://json-schema.org/draft/2020-12/schema",
            "type": "object",
            "properties": {
                "query": {
                    "type": "string"
                }
            },
            "required": [
                "query"
            ],
            "additionalProperties": false
        },
        "sector.set_beacon": {
            "$id": "ge://schema/sector.set_beacon.json",
            "$schema": "https://json-schema.org/draft/2020-12/schema",
            "type": "object",
            "properties": {
                "sector_id": {
                    "type": "integer"
                },
                "text": {
                    "type": "string"
                }
            },
            "required": [
                "sector_id",
                "text"
            ],
            "additionalProperties": false
        },
        "session.disconnect": {
            "$id": "ge://schema/session.disconnect.json",
            "$schema": "https://json-schema.org/draft/2020-12/schema",
            "type": "object",
            "properties": {},
            "additionalProperties": false
        },
        "session.ping": {
            "$id": "ge://schema/session.ping.json",
            "$schema": "https://json-schema.org/draft/2020-12/schema",
            "type": "object",
            "properties": {},
            "required": [],
            "additionalProperties": false
        },
        "sys.notice.create": {
            "$id": "ge://schema/sys.notice.create.json",
            "$schema": "https://json-schema.org/draft/2020-12/schema",
            "type": "object",
            "properties": {
                "title": {
                    "type": "string"
                },
                "body": {
                    "type": "string"
                },
                "severity": {
                    "type": "string"
                },
                "expires_at": {
                    "type": "integer"
                }
            },
            "required": [
                "title",
                "body"
            ],
            "additionalProperties": false
        },
        "sys.cron.planet_tick_once": {
            "$id": "ge://schema/placeholder.json",
            "$comment": "Not yet implemented",
            "type": "object"
        },
        "sys.cron.citadel_reap_once": {
            "$id": "ge://schema/placeholder.json",
            "$comment": "Not yet implemented",
            "type": "object"
        },
        "system.disconnect": {
            "$id": "ge://schema/system.disconnect.json",
            "$schema": "https://json-schema.org/draft/2020-12/schema",
            "type": "object",
            "properties": {},
            "additionalProperties": false
        },
        "ship.claim": {
            "$id": "ge://schema/ship.claim.json",
            "$schema": "https://json-schema.org/draft/2020-12/schema",
            "type": "object",
            "properties": {
                "ship_id": {
                    "type": "integer",
                    "minimum": 1
                }
            },
            "required": [
                "ship_id"
            ],
            "additionalProperties": false
        },
        "ship.info": {
            "$id": "ge://schema/ship.info.json",
            "$schema": "https://json-schema.org/draft/2020-12/schema",
            "type": "object",
            "properties": {},
            "required": [],
            "additionalProperties": false
        },
        "ship.inspect": {
            "$id": "ge://schema/ship.inspect.json",
            "$schema": "https://json-schema.org/draft/2020-12/schema",
            "type": "object",
            "properties": {
                "ship_id": {
                    "type": "integer",
                    "minimum": 1
                }
            },
            "required": [
                "ship_id"
            ],
            "additionalProperties": false
        },
        "ship.jettison": {
            "$id": "ge://schema/ship.jettison.json",
            "$schema": "https://json-schema.org/draft/2020-12/schema",
            "type": "object",
            "properties": {
                "commodity_id": {
                    "type": "integer",
                    "minimum": 1
                },
                "quantity": {
                    "type": "integer",
                    "minimum": 1
                }
            },
            "required": [
                "commodity_id",
                "quantity"
            ],
            "additionalProperties": false
        },
        "ship.list": {
            "$id": "ge://schema/placeholder.json",
            "$comment": "Not yet implemented",
            "type": "object"
        },
        "ship.rename": {
            "$id": "ge://schema/ship.rename.json",
            "$schema": "https://json-schema.org/draft/2020-12/schema",
            "type": "object",
            "properties": {
                "name": {
                    "type": "string",
                    "minLength": 1,
                    "maxLength": 100
                }
            },
            "required": [
                "name"
            ],
            "additionalProperties": false
        },
        "ship.repair": {
            "$id": "ge://schema/ship.repair.json",
            "$schema": "https://json-schema.org/draft/2020-12/schema",
            "type": "object",
            "properties": {},
            "additionalProperties": false
        },
        "ship.reregister": {
            "$id": "ge://schema/ship.reregister.json",
            "$schema": "https://json-schema.org/draft/2020-12/schema",
            "type": "object",
            "properties": {
                "name": {
                    "type": "string",
                    "minLength": 1,
                    "maxLength": 100
                }
            },
            "required": [
                "name"
            ],
            "additionalProperties": false
        },
        "ship.self_destruct": {
            "$id": "ge://schema/ship.self_destruct.json",
            "$schema": "https://json-schema.org/draft/2020-12/schema",
            "type": "object",
            "properties": {},
            "additionalProperties": false
        },
        "ship.sell": {
            "$id": "ge://schema/placeholder.json",
            "$comment": "Not yet implemented",
            "type": "object"
        },
        "ship.status": {
            "$id": "ge://schema/ship.status.json",
            "$schema": "https://json-schema.org/draft/2020-12/schema",
            "type": "object",
            "properties": {},
            "required": [],
            "additionalProperties": false
        },
        "ship.tow": {
            "$id": "ge://schema/placeholder.json",
            "$comment": "Not yet implemented",
            "type": "object"
        },
        "ship.transfer": {
            "$id": "ge://schema/placeholder.json",
            "$comment": "Not yet implemented",
            "type": "object"
        },
        "ship.transfer_cargo": {
            "$id": "ge://schema/ship.transfer_cargo.json",
            "$schema": "https://json-schema.org/draft/2020-12/schema",
            "type": "object",
            "properties": {
                "commodity_id": {
                    "type": "integer",
                    "minimum": 1
                },
                "quantity": {
                    "type": "integer",
                    "minimum": 1
                },
                "target_ship_id": {
                    "type": "integer",
                    "minimum": 1
                }
            },
            "required": [
                "commodity_id",
                "quantity",
                "target_ship_id"
            ],
            "additionalProperties": false
        },
        "ship.upgrade": {
            "$id": "ge://schema/ship.upgrade.json",
            "$schema": "https://json-schema.org/draft/2020-12/schema",
            "type": "object",
            "properties": {
                "upgrade_type": {
                    "type": "string"
                }
            },
            "required": [
                "upgrade_type"
            ],
            "additionalProperties": false
        },
        "shipyard.list": {
            "$id": "ge://schema/placeholder.json",
            "$comment": "Not yet implemented",
            "type": "object"
        },
        "shipyard.sell": {
            "$id": "ge://schema/placeholder.json",
            "$comment": "Not yet implemented",
            "type": "object"
        },
        "shipyard.upgrade": {
            "$id": "ge://schema/placeholder.json",
            "$comment": "Not yet implemented",
            "type": "object"
        },
        "equity.buy": {
            "$id": "ge://schema/placeholder.json",
            "$comment": "Not yet implemented",
            "type": "object"
        },
        "equity.sell": {
            "$id": "ge://schema/placeholder.json",
            "$comment": "Not yet implemented",
            "type": "object"
        },
        "equity.ipo_register": {
            "$id": "ge://schema/placeholder.json",
            "$comment": "Not yet implemented",
            "type": "object"
        },
        "equity.dividend_set": {
            "$id": "ge://schema/placeholder.json",
            "$comment": "Not yet implemented",
            "type": "object"
        },
        "equity.exchange.list": {
            "$id": "ge://schema/placeholder.json",
            "$comment": "Not yet implemented",
            "type": "object"
        },
        "equity.exchange.order.create": {
            "$id": "ge://schema/placeholder.json",
            "$comment": "Not yet implemented",
            "type": "object"
        },
        "equity.exchange.order.cancel": {
            "$id": "ge://schema/placeholder.json",
            "$comment": "Not yet implemented",
            "type": "object"
        },
        "equity.portfolio.list": {
            "$id": "ge://schema/placeholder.json",
            "$comment": "Not yet implemented",
            "type": "object"
        },
        "stock.buy": {
            "$id": "ge://schema/placeholder.json",
            "$comment": "Not yet implemented",
            "type": "object"
        },
        "stock.sell": {
            "$id": "ge://schema/placeholder.json",
            "$comment": "Not yet implemented",
            "type": "object"
        },
        "stock.dividend.set": {
            "$id": "ge://schema/placeholder.json",
            "$comment": "Not yet implemented",
            "type": "object"
        },
        "stock.exchange.list_stocks": {
            "$id": "ge://schema/placeholder.json",
            "$comment": "Not yet implemented",
            "type": "object"
        },
        "stock.exchange.orders.cancel": {
            "$id": "ge://schema/placeholder.json",
            "$comment": "Not yet implemented",
            "type": "object"
        },
        "stock.exchange.orders.create": {
            "$id": "ge://schema/placeholder.json",
            "$comment": "Not yet implemented",
            "type": "object"
        },
        "stock.ipo.register": {
            "$id": "ge://schema/placeholder.json",
            "$comment": "Not yet implemented",
            "type": "object"
        },
        "stock.portfolio.list": {
            "$id": "ge://schema/placeholder.json",
            "$comment": "Not yet implemented",
            "type": "object"
        },
        "subscribe.add": {
            "$id": "ge://schema/subscribe.add.json",
            "$schema": "https://json-schema.org/draft/2020-12/schema",
            "type": "object",
            "properties": {
                "event_type": {
                    "type": "string"
                }
            },
            "required": [
                "event_type"
            ],
            "additionalProperties": false
        },
        "subscribe.catalog": {
            "$id": "ge://schema/subscribe.catalog.json",
            "$schema": "https://json-schema.org/draft/2020-12/schema",
            "type": "object",
            "properties": {},
            "required": [],
            "additionalProperties": false
        },
        "subscribe.list": {
            "$id": "ge://schema/subscribe.list.json",
            "$schema": "https://json-schema.org/draft/2020-12/schema",
            "type": "object",
            "properties": {},
            "additionalProperties": false
        },
        "subscribe.remove": {
            "$id": "ge://schema/subscribe.remove.json",
            "$schema": "https://json-schema.org/draft/2020-12/schema",
            "type": "object",
            "properties": {
                "event_type": {
                    "type": "string"
                }
            },
            "required": [
                "event_type"
            ],
            "additionalProperties": false
        },
        "tavern.barcharts.get_prices_summary": {
            "$id": "ge://schema/placeholder.json",
            "$comment": "Not yet implemented",
            "type": "object"
        },
        "tavern.deadpool.place_bet": {
            "$id": "ge://schema/placeholder.json",
            "$comment": "Not yet implemented",
            "type": "object"
        },
        "tavern.dice.play": {
            "$id": "ge://schema/placeholder.json",
            "$comment": "Not yet implemented",
            "type": "object"
        },
        "tavern.graffiti.post": {
            "$id": "ge://schema/placeholder.json",
            "$comment": "Not yet implemented",
            "type": "object"
        },
        "tavern.highstakes.play": {
            "$id": "ge://schema/placeholder.json",
            "$comment": "Not yet implemented",
            "type": "object"
        },
        "tavern.loan.pay": {
            "$id": "ge://schema/placeholder.json",
            "$comment": "Not yet implemented",
            "type": "object"
        },
        "tavern.loan.take": {
            "$id": "ge://schema/placeholder.json",
            "$comment": "Not yet implemented",
            "type": "object"
        },
        "tavern.lottery.buy_ticket": {
            "$id": "ge://schema/placeholder.json",
            "$comment": "Not yet implemented",
            "type": "object"
        },
        "tavern.lottery.status": {
            "$id": "ge://schema/placeholder.json",
            "$comment": "Not yet implemented",
            "type": "object"
        },
        "tavern.raffle.buy_ticket": {
            "$id": "ge://schema/placeholder.json",
            "$comment": "Not yet implemented",
            "type": "object"
        },
        "tavern.round.buy": {
            "$id": "ge://schema/placeholder.json",
            "$comment": "Not yet implemented",
            "type": "object"
        },
        "tavern.rumour.get_hint": {
            "$id": "ge://schema/placeholder.json",
            "$comment": "Not yet implemented",
            "type": "object"
        },
        "tavern.trader.buy_password": {
            "$id": "ge://schema/placeholder.json",
            "$comment": "Not yet implemented",
            "type": "object"
        },
        "trade.accept": {
            "$id": "ge://schema/trade.accept.json",
            "$schema": "https://json-schema.org/draft/2020-12/schema",
            "type": "object",
            "properties": {
                "trade_id": {
                    "type": "integer",
                    "minimum": 1
                }
            },
            "required": [
                "trade_id"
            ],
            "additionalProperties": false
        },
        "trade.buy": {
            "$id": "ge://schema/trade.buy.json",
            "$schema": "https://json-schema.org/draft/2020-12/schema",
            "type": "object",
            "required": [
                "port_id",
                "items",
                "idempotency_key",
                "account",
                "sector_id"
            ],
            "additionalProperties": false,
            "properties": {
                "port_id": {
                    "type": "integer"
                },
                "idempotency_key": {
                    "type": "string"
                },
                "account": {
                    "type": "integer",
                    "enum": [
                        0,
                        1
                    ]
                },
                "sector_id": {
                    "type": "integer"
                },
                "items": {
                    "type": "array",
                    "items": {
                        "type": "object",
                        "required": [
                            "commodity",
                            "quantity"
                        ],
                        "additionalProperties": false,
                        "properties": {
                            "commodity": {
                                "type": "string"
                            },
                            "quantity": {
                                "type": "integer"
                            }
                        }
                    }
                }
            }
        },
        "trade.cancel": {
            "$id": "ge://schema/trade.cancel.json",
            "$schema": "https://json-schema.org/draft/2020-12/schema",
            "type": "object",
            "properties": {
                "trade_id": {
                    "type": "integer",
                    "minimum": 1
                }
            },
            "required": [
                "trade_id"
            ],
            "additionalProperties": false
        },
        "trade.history": {
            "$id": "ge://schema/trade.history.json",
            "$schema": "https://json-schema.org/draft/2020-12/schema",
            "type": "object",
            "required": [],
            "additionalProperties": false,
            "properties": {
                "limit": {
                    "type": "integer",
                    "minimum": 1,
                    "maximum": 50
                },
                "cursor": {
                    "type": "string"
                }
            }
        },
        "trade.jettison": {
            "$id": "ge://schema/trade.jettison.json",
            "$schema": "https://json-schema.org/draft/2020-12/schema",
            "type": "object",
            "properties": {
                "commodity": {
                    "type": "string"
                },
                "quantity": {
                    "type": "integer",
                    "minimum": 1
                }
            },
            "required": [
                "commodity",
                "quantity"
            ],
            "additionalProperties": false
        },
        "trade.offer": {
            "$id": "ge://schema/trade.offer.json",
            "$schema": "https://json-schema.org/draft/2020-12/schema",
            "type": "object",
            "properties": {
                "trade_id": {
                    "type": "integer",
                    "minimum": 1
                }
            },
            "required": [
                "trade_id"
            ],
            "additionalProperties": false
        },
        "trade.port_info": {
            "$id": "ge://schema/trade.port_info.json",
            "$schema": "https://json-schema.org/draft/2020-12/schema",
            "type": "object",
            "properties": {},
            "additionalProperties": false
        },
        "trade.quote": {
            "$id": "ge://schema/trade.quote.json",
            "$schema": "https://json-schema.org/draft/2020-12/schema",
            "type": "object",
            "properties": {
                "port_id": {
                    "type": "integer"
                },
                "commodity": {
                    "type": "string"
                },
                "quantity": {
                    "type": "integer"
                }
            },
            "required": [
                "port_id",
                "commodity",
                "quantity"
            ],
            "additionalProperties": false
        },
        "trade.sell": {
            "$id": "ge://schema/trade.sell.json",
            "$schema": "https://json-schema.org/draft/2020-12/schema",
            "type": "object",
            "required": [
                "sector_id",
                "port_id",
                "items",
                "idempotency_key",
                "account"
            ],
            "additionalProperties": false,
            "properties": {
                "sector_id": {
                    "type": "integer"
                },
                "port_id": {
                    "type": "integer"
                },
                "idempotency_key": {
                    "type": "string"
                },
                "account": {
                    "type": "integer",
                    "enum": [
                        0,
                        1
                    ]
                },
                "items": {
                    "type": "array",
                    "items": {
                        "type": "object",
                        "required": [
                            "commodity",
                            "quantity"
                        ],
                        "additionalProperties": false,
                        "properties": {
                            "commodity": {
                                "type": "string"
                            },
                            "quantity": {
                                "type": "integer"
                            }
                        }
                    }
                }
            }
        }
    },
    "schema_blacklist": [],
    "pending_schema_requests": {
        "system.cmd_list": "c-24fcce8c",
        "admin.notice": "c-f5a55a59",
        "admin.shutdown_warning": "c-ca974df8",
        "auth.login": "c-d12f345d",
        "auth.logout": "c-70af88d3",
        "auth.mfa.totp.verify": "c-375597f0",
        "auth.register": "c-c997b84d",
        "auth.refresh": "c-10bd1357",
        "auth.change_password": "c-528ce9c3",
        "bank.balance": "c-30817480",
        "bank.deposit": "c-24081543",
        "bank.history": "c-c0af47e7",
        "bank.leaderboard": "c-e4af50d2",
        "bank.transfer": "c-13d209fb",
        "bank.withdraw": "c-bcfd41ef",
        "bounty.list": "c-756a1a69",
        "bounty.post_federation": "c-4129cddf",
        "bounty.post_hitlist": "c-cb0b87c6",
        "bulk.execute": "c-e199d992",
        "fine.list": "c-77ae2a15",
        "fine.pay": "c-e60c8957",
        "insurance.policies.list": "c-f547f4fa",
        "insurance.policies.buy": "c-861ea8fd",
        "insurance.claim.file": "c-bfcaf6b7",
        "chat.broadcast": "c-1bfcbed3",
        "chat.history": "c-86379ddb",
        "chat.send": "c-9cc514dc",
        "citadel.build": "c-d706917b",
        "citadel.upgrade": "c-eeafa44b",
        "combat.attack": "c-b520f9ec",
        "combat.attack_planet": "c-d9af6f78",
        "combat.deploy_fighters": "c-92858949",
        "combat.deploy_mines": "c-42fe3e13",
        "combat.lay_mines": "c-e59eb3f9",
        "combat.status": "c-826a0df6",
        "combat.sweep_mines": "c-be1eae38",
        "deploy.fighters.list": "c-bbbfa842",
        "deploy.mines.list": "c-c794ea82",
        "fighters.recall": "c-c21103ab",
        "mines.recall": "c-fbecc063",
        "corp.balance": "c-23f6d50c",
        "corp.create": "c-43d2aa27",
        "corp.deposit": "c-c2ca81ec",
        "corp.dissolve": "c-2395266a",
        "corp.invite": "c-2b865292",
        "corp.join": "c-2636f66c",
        "corp.kick": "c-f3c032ca",
        "corp.leave": "c-78dc41e0",
        "corp.list": "c-dcdfced8",
        "corp.roster": "c-cef261f1",
        "corp.statement": "c-53d83d3a",
        "corp.status": "c-0252450b",
        "corp.transfer_ceo": "c-2edae021",
        "corp.withdraw": "c-e099419c",
        "dock.status": "c-5e37c6f8",
        "hardware.buy": "c-6268b37c",
        "hardware.list": "c-045d3ea9",
        "mail.delete": "c-93ac6ebc",
        "mail.inbox": "c-6452e96f",
        "mail.read": "c-e63a6f8f",
        "mail.send": "c-203764c2",
        "move.autopilot.start": "c-4dd91c76",
        "move.autopilot.status": "c-e7715f71",
        "move.autopilot.stop": "c-400d20b4",
        "move.describe_sector": "c-ef93b50a",
        "move.pathfind": "c-58ca4c4b",
        "move.scan": "c-7861ea42",
        "move.transwarp": "c-586197fb",
        "move.warp": "c-f028733b",
        "nav.avoid.add": "c-5b138b8f",
        "nav.avoid.list": "c-43d2c5a7",
        "nav.avoid.remove": "c-9562efa8",
        "nav.avoid.set": "c-0c4ae760",
        "nav.bookmark.add": "c-25ce5915",
        "nav.bookmark.list": "c-75aa9ced",
        "nav.bookmark.remove": "c-226928f5",
        "nav.bookmark.set": "c-173db4d6",
        "news.get_feed": "c-52ff5617",
        "news.mark_feed_read": "c-08b9bc4c",
        "news.read": "c-a9b796c7",
        "notes.delete": "c-6da7ac50",
        "notes.list": "c-0015579f",
        "notes.set": "c-93a59ffe",
        "notice.ack": "c-2223e6fd",
        "notice.list": "c-d70ff8f2",
        "planet.create": "c-8962194f",
        "planet.deposit": "c-db50158e",
        "planet.genesis": "c-c1653775",
        "planet.genesis_create": "c-00a58a34",
        "planet.harvest": "c-80bafab3",
        "planet.info": "c-6cee0697",
        "planet.land": "c-ce09dc05",
        "planet.launch": "c-2c76d875",
        "planet.market.buy_order": "c-29c3b844",
        "planet.market.sell": "c-97282757",
        "planet.rename": "c-7b506443",
        "planet.transfer_ownership": "c-1f700238",
        "planet.withdraw": "c-0b0d0a40",
        "sysop.config.list": "c-f02e5ff5",
        "sysop.config.get": "c-5aad9796",
        "sysop.config.set": "c-bcfac905",
        "sysop.config.history": "c-46de0130",
        "sysop.players.search": "c-95e64b5b",
        "sysop.player.get": "c-b7f66ec1",
        "sysop.player.kick": "c-bbeed4ef",
        "sysop.player.sessions.get": "c-7ebfd797",
        "sysop.universe.summary": "c-7bb9dc33",
        "sysop.engine_status.get": "c-37b48ad8",
        "sysop.jobs.list": "c-83f154e2",
        "sysop.jobs.get": "c-714dd0ad",
        "sysop.jobs.retry": "c-2c70b768",
        "sysop.jobs.cancel": "c-9062f51c",
        "sysop.notice.create": "c-2af274bd",
        "sysop.notice.delete": "c-da542f2e",
        "sysop.broadcast.send": "c-b6a2a45c",
        "sysop.logs.tail": "c-c042d3c3",
        "sysop.logs.clear": "c-583b4455",
        "player.get_avoids": "c-3f0a9c7c",
        "player.get_bookmarks": "c-83620bd0",
        "player.get_notes": "c-b77bc2c5",
        "player.get_prefs": "c-391de69c",
        "player.get_settings": "c-d4a94538",
        "player.get_subscriptions": "c-a2f48a6c",
        "player.get_topics": "c-7b35cdd0",
        "player.my_info": "c-30fdd71d",
        "player.rankings": "c-9dadb8bb",
        "player.computer.recommend_routes": "c-f038457a",
        "player.set_avoids": "c-740e9400",
        "player.set_bookmarks": "c-c4a21858",
        "player.set_prefs": "c-e5720120",
        "player.set_settings": "c-f962d386",
        "player.set_subscriptions": "c-d0f71b20",
        "player.set_topics": "c-a839e6b8",
        "player.set_trade_account_preference": "c-9075654b",
        "port.describe": "c-6d58706c",
        "port.info": "c-46895595",
        "port.rob": "c-15f50e3b",
        "port.status": "c-fa6c7e9a",
        "s2s.planet.genesis": "c-2dad38a8",
        "s2s.planet_genesis": "c-b165b59b",
        "sector.info": "c-d210a840",
        "sector.mine_disrupt": "c-b434baf7",
        "sector.scan": "c-cb1c7e26",
        "sector.scan.density": "c-9ba00aad",
        "sector.search": "c-1e79706b",
        "sector.set_beacon": "c-55523a4d",
        "session.disconnect": "c-d22d113e",
        "session.ping": "c-01dec5e7",
        "sys.notice.create": "c-77ffb5d9",
        "sys.cron.planet_tick_once": "c-4a7c35d1",
        "sys.cron.citadel_reap_once": "c-32e62070",
        "system.disconnect": "c-f7ccbc03",
        "ship.claim": "c-bb806242",
        "ship.info": "c-a78a23bd",
        "ship.inspect": "c-0dee1276",
        "ship.jettison": "c-a538aad7",
        "ship.list": "c-c3be053a",
        "ship.rename": "c-63d00e26",
        "ship.repair": "c-1ee0b709",
        "ship.reregister": "c-a0d9c995",
        "ship.self_destruct": "c-c1a92731",
        "ship.sell": "c-f91ee88e",
        "ship.status": "c-42cd815e",
        "ship.tow": "c-119c54bc",
        "ship.transfer": "c-6468efe9",
        "ship.transfer_cargo": "c-599024cf",
        "ship.upgrade": "c-5098cd9e",
        "shipyard.list": "c-cfb5e50c",
        "shipyard.sell": "c-7ec0deda",
        "shipyard.upgrade": "c-fed6c60d",
        "equity.buy": "c-f25b464f",
        "equity.sell": "c-5cd88dc7",
        "equity.ipo_register": "c-b949a72e",
        "equity.dividend_set": "c-c130d613",
        "equity.exchange.list": "c-64c9b9ec",
        "equity.exchange.order.create": "c-e1c65273",
        "equity.exchange.order.cancel": "c-33292678",
        "equity.portfolio.list": "c-a16e24bb",
        "stock.buy": "c-84081c30",
        "stock.sell": "c-88295d9e",
        "stock.dividend.set": "c-b766ca77",
        "stock.exchange.list_stocks": "c-bce14494",
        "stock.exchange.orders.cancel": "c-9b8395f7",
        "stock.exchange.orders.create": "c-dd7779d6",
        "stock.ipo.register": "c-6f29ec7c",
        "stock.portfolio.list": "c-2a649f1e",
        "subscribe.add": "c-883d0312",
        "subscribe.catalog": "c-9bb2e631",
        "subscribe.list": "c-fb475866",
        "subscribe.remove": "c-29c77e55",
        "tavern.barcharts.get_prices_summary": "c-98f05545",
        "tavern.deadpool.place_bet": "c-a58c0719",
        "tavern.dice.play": "c-1db73c56",
        "tavern.graffiti.post": "c-9b172293",
        "tavern.highstakes.play": "c-16b8ad2e",
        "tavern.loan.pay": "c-7e7f0931",
        "tavern.loan.take": "c-f2157476",
        "tavern.lottery.buy_ticket": "c-960dc7b7",
        "tavern.lottery.status": "c-68fdf919",
        "tavern.raffle.buy_ticket": "c-3c988c6d",
        "tavern.round.buy": "c-801b2270",
        "tavern.rumour.get_hint": "c-fb84b7a1",
        "tavern.trader.buy_password": "c-03bbe2c4",
        "trade.accept": "c-f2da1fc1",
        "trade.buy": "c-6c516408",
        "trade.cancel": "c-124233c7",
        "trade.history": "c-f82a0fe2",
        "trade.jettison": "c-84b6312d",
        "trade.offer": "c-87d39959",
        "trade.port_info": "c-786c145e",
        "trade.quote": "c-64544d4c",
        "trade.sell": "c-eaa8bfc4"
    },
    "recent_sectors": [
        2,
        8,
        9,
        10,
        2,
        1
    ],
    "pending_commands": {},
    "port_trade_blacklist": [],
    "warp_blacklist": [],
    "current_path": [],
    "last_action_result": {
        "status": "ok",
        "command": "trade.quote",
        "request_id": "c-8558f0ce",
        "response_type": "trade.quote",
        "ts": "2026-02-02T21:54:55Z"
    },
    "last_quotes": {},
    "command_sent_in_response_loop": false,
    "last_port_trade": null,
    "current_qa_objective": "test bounty hunting",
    "needs_bootstrap": false
}