{
    "session_id": "8d71fa3511fddd257b978e78517798c11bb87fc319f90a751dfa6b8789791398",
    "player_info": {
        "player": {
            "id": 21,
            "username": "\u0001",
            "credits": "1000000.00",
            "turns_remaining": 750,
            "sector": 6,
            "ship_id": 32,
            "corp_id": 0,
            "alignment": 1,
            "experience": 0,
            "title_info": {
                "title": "Civilian",
                "commission": 1,
                "alignment": 1,
                "experience": 0,
                "alignment_band": {
                    "code": "NEUTRAL",
                    "name": "Neutral",
                    "is_good": false,
                    "is_evil": false,
                    "can_buy_iss": false,
                    "can_rob_ports": false
                }
            }
        }
    },
    "ship_info": {
        "cargo": []
    },
    "player_location_sector": 6,
    "sector_data": {},
    "universe_map": {
        "6": {
            "is_explored": true,
            "has_port": false
        }
    },
    "port_info_by_sector": {},
    "price_cache": {},
    "bank_balance": 0,
    "command_retry_info": {
        "player.my_info": {
            "next_retry_time": 1765402696.7437832
        }
    },
    "strategy_plan": [],
    "trade_successful": false,
    "q_table": {},
    "n_table": {},
    "command_schemas": {
        "session.hello": {
            "$id": "ge://schema/session.hello.json",
            "$schema": "https://json-schema.org/draft/2020-12/schema",
            "type": "object",
            "properties": {},
            "required": [],
            "additionalProperties": true
        },
        "session.ping": {
            "$id": "ge://schema/session.ping.json",
            "$schema": "https://json-schema.org/draft/2020-12/schema",
            "type": "object",
            "properties": {},
            "required": [],
            "additionalProperties": true
        },
        "session.disconnect": {
            "$id": "ge://schema/session.disconnect.json",
            "$comment": "Schema not yet implemented"
        },
        "auth.login": {
            "$id": "ge://schema/auth.login.json",
            "$schema": "https://json-schema.org/draft/2020-12/schema",
            "type": "object",
            "properties": {
                "username": {
                    "type": "string"
                },
                "passwd": {
                    "type": "string"
                }
            },
            "required": [
                "username",
                "passwd"
            ],
            "additionalProperties": true
        },
        "auth.logout": {
            "$id": "ge://schema/auth.logout.json",
            "$comment": "Schema not yet implemented"
        },
        "auth.mfa.totp.verify": {
            "$id": "ge://schema/auth.mfa.totp.verify.json",
            "$comment": "Schema not yet implemented"
        },
        "auth.register": {
            "$id": "ge://schema/auth.register.json",
            "$schema": "https://json-schema.org/draft/2020-12/schema",
            "type": "object",
            "properties": {
                "username": {
                    "type": "string"
                },
                "passwd": {
                    "type": "string"
                },
                "ship_name": {
                    "type": "string"
                },
                "ui_locale": {
                    "type": "string"
                },
                "ui_timezone": {
                    "type": "string"
                }
            },
            "required": [
                "username",
                "passwd"
            ],
            "additionalProperties": true
        },
        "player.my_info": {
            "$id": "ge://schema/player.my_info.json",
            "$schema": "https://json-schema.org/draft/2020-12/schema",
            "type": "object",
            "properties": {},
            "required": [],
            "additionalProperties": true
        },
        "ship.info": {
            "$id": "ge://schema/ship.info.json",
            "$schema": "https://json-schema.org/draft/2020-12/schema",
            "type": "object",
            "properties": {},
            "additionalProperties": true
        },
        "sector.info": {
            "$id": "ge://schema/sector.info.json",
            "$schema": "https://json-schema.org/draft/2020-12/schema",
            "type": "object",
            "properties": {
                "sector_id": {
                    "type": "integer"
                }
            },
            "required": [],
            "additionalProperties": true
        },
        "sector.set_beacon": {
            "$id": "ge://schema/sector.set_beacon.json",
            "$schema": "https://json-schema.org/draft/2020-12/schema",
            "type": "object",
            "properties": {
                "sector_id": {
                    "type": "integer"
                },
                "text": {
                    "type": "string"
                }
            },
            "required": [
                "sector_id",
                "text"
            ],
            "additionalProperties": false
        },
        "move.warp": {
            "$id": "ge://schema/move_warp.json",
            "$schema": "https://json-schema.org/draft/2020-12/schema",
            "type": "object",
            "properties": {
                "to_sector_id": {
                    "type": "integer"
                }
            },
            "required": [
                "to_sector_id"
            ],
            "additionalProperties": true
        },
        "move.scan": {
            "$id": "ge://schema/move.scan.json",
            "$schema": "https://json-schema.org/draft/2020-12/schema",
            "type": "object",
            "properties": {}
        },
        "move.pathfind": {
            "$id": "ge://schema/move.pathfind.json",
            "$comment": "Schema not yet implemented"
        },
        "trade.accept": {
            "$id": "ge://schema/trade.accept.json",
            "$comment": "Schema not yet implemented"
        },
        "trade.buy": {
            "$id": "ge://schema/trade.buy.json",
            "$schema": "https://json-schema.org/draft/2020-12/schema",
            "type": "object",
            "properties": {
                "port_id": {
                    "type": "integer"
                },
                "items": {
                    "type": "array",
                    "items": {
                        "type": "object",
                        "properties": {
                            "commodity": {
                                "type": "string"
                            },
                            "quantity": {
                                "type": "integer"
                            }
                        },
                        "required": [
                            "commodity",
                            "quantity"
                        ],
                        "additionalProperties": true
                    }
                },
                "idempotency_key": {
                    "type": "string"
                },
                "account": {
                    "type": "integer",
                    "enum": [
                        0,
                        1
                    ]
                },
                "sector_id": {
                    "type": "integer"
                }
            },
            "required": [
                "port_id",
                "items",
                "idempotency_key",
                "account",
                "sector_id"
            ],
            "additionalProperties": true
        },
        "trade.cancel": {
            "$id": "ge://schema/trade.cancel.json",
            "$comment": "Schema not yet implemented"
        },
        "trade.history": {
            "$id": "ge://schema/trade.history.json",
            "$schema": "https://json-schema.org/draft/2020-12/schema",
            "type": "object",
            "properties": {
                "limit": {
                    "type": "integer",
                    "minimum": 1,
                    "maximum": 50
                },
                "cursor": {
                    "type": "string"
                }
            },
            "required": [],
            "additionalProperties": true
        },
        "trade.jettison": {
            "$id": "ge://schema/trade.jettison.json",
            "$comment": "Schema not yet implemented"
        },
        "trade.offer": {
            "$id": "ge://schema/trade.offer.json",
            "$comment": "Schema not yet implemented"
        },
        "trade.port_info": {
            "$id": "ge://schema/trade.port_info.json",
            "$comment": "Schema not yet implemented"
        },
        "trade.quote": {
            "$id": "ge://schema/trade.quote.json",
            "$schema": "https://json-schema.org/draft/2020-12/schema",
            "type": "object",
            "properties": {
                "port_id": {
                    "type": "integer"
                },
                "commodity": {
                    "type": "string"
                },
                "quantity": {
                    "type": "integer"
                }
            },
            "required": [
                "port_id",
                "commodity",
                "quantity"
            ],
            "additionalProperties": true
        },
        "trade.sell": {
            "$id": "ge://schema/trade.sell.json",
            "$schema": "https://json-schema.org/draft/2020-12/schema",
            "type": "object",
            "properties": {
                "sector_id": {
                    "type": "integer"
                },
                "port_id": {
                    "type": "integer"
                },
                "items": {
                    "type": "array",
                    "items": {
                        "type": "object",
                        "properties": {
                            "commodity": {
                                "type": "string"
                            },
                            "quantity": {
                                "type": "integer"
                            }
                        },
                        "required": [
                            "commodity",
                            "quantity"
                        ],
                        "additionalProperties": true
                    }
                },
                "idempotency_key": {
                    "type": "string"
                },
                "account": {
                    "type": "integer",
                    "enum": [
                        0,
                        1
                    ]
                }
            },
            "required": [
                "sector_id",
                "port_id",
                "items",
                "idempotency_key",
                "account"
            ],
            "additionalProperties": true
        }
    },
    "schema_blacklist": [],
    "pending_schema_requests": {
        "system.cmd_list": "c-e0c60773",
        "session.hello": "c-d2593c1b",
        "session.ping": "c-77a6ab1c",
        "session.disconnect": "c-6dc37e79",
        "auth.login": "c-ff76d699",
        "auth.logout": "c-7ba35455",
        "auth.mfa.totp.verify": "c-3a8bc8cd",
        "auth.register": "c-40c0a9df",
        "player.my_info": "c-10ec78ef",
        "ship.info": "c-5c9f9959",
        "sector.info": "c-a6f37951",
        "sector.set_beacon": "c-ca4b71ce",
        "move.warp": "c-49e09094",
        "move.scan": "c-f6d78474",
        "move.pathfind": "c-912f7483",
        "trade.accept": "c-ca81324f",
        "trade.buy": "c-e6c9636b",
        "trade.cancel": "c-651e1476",
        "trade.history": "c-057b2889",
        "trade.jettison": "c-62ed05c2",
        "trade.offer": "c-727404b1",
        "trade.port_info": "c-98e7ae12",
        "trade.quote": "c-b55782ad",
        "trade.sell": "c-4efed335"
    },
    "recent_sectors": [
        6
    ],
    "pending_commands": {},
    "port_trade_blacklist": [],
    "warp_blacklist": [],
    "current_path": [],
    "last_action_result": {
        "status": "ok",
        "command": "player.my_info",
        "request_id": "c-6185c72c",
        "response_type": "player.info",
        "ts": "2025-12-10T21:38:11Z"
    },
    "current_qa_objective": null,
    "needs_bootstrap": true
}